Workbook

Sheet Dashboard
A1: Chirala Bay Resort PMS — Development Control Dashboard
A2: Scope: 130 planned screens | 120 screen designs completed | Development tracking starts at Not Started | Update the Screen Requirements sheet to drive this dashboard
A4: Total Screens | D4: Designs Completed | G4: Development Done | J4: Overall Progress
A5: =COUNTA('Screen Requirements'!$B$5:$B$134) | D5: =COUNTIF('Screen Requirements'!$C$5:$C$134,"Completed") | G5: =COUNTIF('Screen Requirements'!$N$5:$N$134,"Done") | J5: =AVERAGE('Screen Requirements'!$O$5:$O$134)
A8: Module Progress | G8: Delivery Sequence | H8: Delivery Sequence | I8: Delivery Sequence | J8: Delivery Sequence | K8: Delivery Sequence | L8: Delivery Sequence
A9: Module | B9: Screens | C9: Done | D9: Average Progress | F9: Phase | G9: Phase Name | H9: Sprint(s) | I9: Weeks | J9: Screens | K9: Status | L9: Progress
A10: Overview | B10: =COUNTIF('Screen Requirements'!$D$5:$D$134,A10) | C10: =COUNTIFS('Screen Requirements'!$D$5:$D$134,A10,'Screen Requirements'!$N$5:$N$134,"Done") | D10: =IF(B10=0,0,SUMIF('Screen Requirements'!$D$5:$D$134,A10,'Screen Requirements'!$O$5:$O$134)/B10) | F10: 1 | G10: Core Platform, Security & Masters | H10: S01-S02 | I10: 4 | J10: 15 | K10: ='Development Plan'!L5 | L10: ='Development Plan'!M5
A11: Front Desk | B11: =COUNTIF('Screen Requirements'!$D$5:$D$134,A11) | C11: =COUNTIFS('Screen Requirements'!$D$5:$D$134,A11,'Screen Requirements'!$N$5:$N$134,"Done") | D11: =IF(B11=0,0,SUMIF('Screen Requirements'!$D$5:$D$134,A11,'Screen Requirements'!$O$5:$O$134)/B11) | F11: 2 | G11: Inventory, Rates & Distribution Foundation | H11: S03-S04 | I11: 4 | J11: 11 | K11: ='Development Plan'!L6 | L11: ='Development Plan'!M6
A12: Reservations | B12: =COUNTIF('Screen Requirements'!$D$5:$D$134,A12) | C12: =COUNTIFS('Screen Requirements'!$D$5:$D$134,A12,'Screen Requirements'!$N$5:$N$134,"Done") | D12: =IF(B12=0,0,SUMIF('Screen Requirements'!$D$5:$D$134,A12,'Screen Requirements'!$O$5:$O$134)/B12) | F12: 3 | G12: Reservations, Groups & Front Desk | H12: S05-S07 | I12: 6 | J12: 21 | K12: ='Development Plan'!L7 | L12: ='Development Plan'!M7
A13: Housekeeping | B13: =COUNTIF('Screen Requirements'!$D$5:$D$134,A13) | C13: =COUNTIFS('Screen Requirements'!$D$5:$D$134,A13,'Screen Requirements'!$N$5:$N$134,"Done") | D13: =IF(B13=0,0,SUMIF('Screen Requirements'!$D$5:$D$134,A13,'Screen Requirements'!$O$5:$O$134)/B13) | F13: 4 | G13: Guest CRM, Privacy & Communications | H13: S08-S09 | I13: 4 | J13: 11 | K13: ='Development Plan'!L8 | L13: ='Development Plan'!M8
A14: Property & Rooms | B14: =COUNTIF('Screen Requirements'!$D$5:$D$134,A14) | C14: =COUNTIFS('Screen Requirements'!$D$5:$D$134,A14,'Screen Requirements'!$N$5:$N$134,"Done") | D14: =IF(B14=0,0,SUMIF('Screen Requirements'!$D$5:$D$134,A14,'Screen Requirements'!$O$5:$O$134)/B14) | F14: 5 | G14: Housekeeping & Guest Services | H14: S10-S11 | I14: 4 | J14: 8 | K14: ='Development Plan'!L9 | L14: ='Development Plan'!M9
A15: Guest CRM | B15: =COUNTIF('Screen Requirements'!$D$5:$D$134,A15) | C15: =COUNTIFS('Screen Requirements'!$D$5:$D$134,A15,'Screen Requirements'!$N$5:$N$134,"Done") | D15: =IF(B15=0,0,SUMIF('Screen Requirements'!$D$5:$D$134,A15,'Screen Requirements'!$O$5:$O$134)/B15) | F15: 6 | G15: Restaurant POS & Kitchen | H15: S12-S13 | I15: 4 | J15: 9 | K15: ='Development Plan'!L10 | L15: ='Development Plan'!M10
A16: Food & Beverage | B16: =COUNTIF('Screen Requirements'!$D$5:$D$134,A16) | C16: =COUNTIFS('Screen Requirements'!$D$5:$D$134,A16,'Screen Requirements'!$N$5:$N$134,"Done") | D16: =IF(B16=0,0,SUMIF('Screen Requirements'!$D$5:$D$134,A16,'Screen Requirements'!$O$5:$O$134)/B16) | F16: 7 | G16: Inventory & Procurement | H16: S14-S15 | I16: 4 | J16: 10 | K16: ='Development Plan'!L11 | L16: ='Development Plan'!M11
A17: Guest Services | B17: =COUNTIF('Screen Requirements'!$D$5:$D$134,A17) | C17: =COUNTIFS('Screen Requirements'!$D$5:$D$134,A17,'Screen Requirements'!$N$5:$N$134,"Done") | D17: =IF(B17=0,0,SUMIF('Screen Requirements'!$D$5:$D$134,A17,'Screen Requirements'!$O$5:$O$134)/B17) | F17: 8 | G17: Maintenance & Asset Operations | H17: S16 | I17: 2 | J17: 6 | K17: ='Development Plan'!L12 | L17: ='Development Plan'!M12
A18: Activities | B18: =COUNTIF('Screen Requirements'!$D$5:$D$134,A18) | C18: =COUNTIFS('Screen Requirements'!$D$5:$D$134,A18,'Screen Requirements'!$N$5:$N$134,"Done") | D18: =IF(B18=0,0,SUMIF('Screen Requirements'!$D$5:$D$134,A18,'Screen Requirements'!$O$5:$O$134)/B18) | F18: 9 | G18: Activities, Spa, Events & Transport | H18: S17-S19 | I18: 6 | J18: 17 | K18: ='Development Plan'!L13 | L18: ='Development Plan'!M13
A19: Spa | B19: =COUNTIF('Screen Requirements'!$D$5:$D$134,A19) | C19: =COUNTIFS('Screen Requirements'!$D$5:$D$134,A19,'Screen Requirements'!$N$5:$N$134,"Done") | D19: =IF(B19=0,0,SUMIF('Screen Requirements'!$D$5:$D$134,A19,'Screen Requirements'!$O$5:$O$134)/B19) | F19: 10 | G19: Workforce, Finance & Analytics | H19: S20-S22 | I19: 6 | J19: 10 | K19: ='Development Plan'!L14 | L19: ='Development Plan'!M14
A20: Events & Banquets | B20: =COUNTIF('Screen Requirements'!$D$5:$D$134,A20) | C20: =COUNTIFS('Screen Requirements'!$D$5:$D$134,A20,'Screen Requirements'!$N$5:$N$134,"Done") | D20: =IF(B20=0,0,SUMIF('Screen Requirements'!$D$5:$D$134,A20,'Screen Requirements'!$O$5:$O$134)/B20) | F20: 11 | G20: Portals, Integrations & AI | H20: S23-S25 | I20: 6 | J20: 11 | K20: ='Development Plan'!L15 | L20: ='Development Plan'!M15
A21: Transport | B21: =COUNTIF('Screen Requirements'!$D$5:$D$134,A21) | C21: =COUNTIFS('Screen Requirements'!$D$5:$D$134,A21,'Screen Requirements'!$N$5:$N$134,"Done") | D21: =IF(B21=0,0,SUMIF('Screen Requirements'!$D$5:$D$134,A21,'Screen Requirements'!$O$5:$O$134)/B21) | F21: 12 | G21: Executive Dashboard, UAT & Release | H21: S26-S27 | I21: 4 | J21: 1 | K21: ='Development Plan'!L16 | L21: ='Development Plan'!M16
A22: Maintenance | B22: =COUNTIF('Screen Requirements'!$D$5:$D$134,A22) | C22: =COUNTIFS('Screen Requirements'!$D$5:$D$134,A22,'Screen Requirements'!$N$5:$N$134,"Done") | D22: =IF(B22=0,0,SUMIF('Screen Requirements'!$D$5:$D$134,A22,'Screen Requirements'!$O$5:$O$134)/B22)
A23: Inventory | B23: =COUNTIF('Screen Requirements'!$D$5:$D$134,A23) | C23: =COUNTIFS('Screen Requirements'!$D$5:$D$134,A23,'Screen Requirements'!$N$5:$N$134,"Done") | D23: =IF(B23=0,0,SUMIF('Screen Requirements'!$D$5:$D$134,A23,'Screen Requirements'!$O$5:$O$134)/B23)
A24: Workforce | B24: =COUNTIF('Screen Requirements'!$D$5:$D$134,A24) | C24: =COUNTIFS('Screen Requirements'!$D$5:$D$134,A24,'Screen Requirements'!$N$5:$N$134,"Done") | D24: =IF(B24=0,0,SUMIF('Screen Requirements'!$D$5:$D$134,A24,'Screen Requirements'!$O$5:$O$134)/B24)
A25: Finance | B25: =COUNTIF('Screen Requirements'!$D$5:$D$134,A25) | C25: =COUNTIFS('Screen Requirements'!$D$5:$D$134,A25,'Screen Requirements'!$N$5:$N$134,"Done") | D25: =IF(B25=0,0,SUMIF('Screen Requirements'!$D$5:$D$134,A25,'Screen Requirements'!$O$5:$O$134)/B25)
A26: Purchasing | B26: =COUNTIF('Screen Requirements'!$D$5:$D$134,A26) | C26: =COUNTIFS('Screen Requirements'!$D$5:$D$134,A26,'Screen Requirements'!$N$5:$N$134,"Done") | D26: =IF(B26=0,0,SUMIF('Screen Requirements'!$D$5:$D$134,A26,'Screen Requirements'!$O$5:$O$134)/B26)
A27: Distribution | B27: =COUNTIF('Screen Requirements'!$D$5:$D$134,A27) | C27: =COUNTIFS('Screen Requirements'!$D$5:$D$134,A27,'Screen Requirements'!$N$5:$N$134,"Done") | D27: =IF(B27=0,0,SUMIF('Screen Requirements'!$D$5:$D$134,A27,'Screen Requirements'!$O$5:$O$134)/B27)
A28: Administration | B28: =COUNTIF('Screen Requirements'!$D$5:$D$134,A28) | C28: =COUNTIFS('Screen Requirements'!$D$5:$D$134,A28,'Screen Requirements'!$N$5:$N$134,"Done") | D28: =IF(B28=0,0,SUMIF('Screen Requirements'!$D$5:$D$134,A28,'Screen Requirements'!$O$5:$O$134)/B28)
A29: Analytics | B29: =COUNTIF('Screen Requirements'!$D$5:$D$134,A29) | C29: =COUNTIFS('Screen Requirements'!$D$5:$D$134,A29,'Screen Requirements'!$N$5:$N$134,"Done") | D29: =IF(B29=0,0,SUMIF('Screen Requirements'!$D$5:$D$134,A29,'Screen Requirements'!$O$5:$O$134)/B29)
A30: Groups | B30: =COUNTIF('Screen Requirements'!$D$5:$D$134,A30) | C30: =COUNTIFS('Screen Requirements'!$D$5:$D$134,A30,'Screen Requirements'!$N$5:$N$134,"Done") | D30: =IF(B30=0,0,SUMIF('Screen Requirements'!$D$5:$D$134,A30,'Screen Requirements'!$O$5:$O$134)/B30)
A31: Revenue Management | B31: =COUNTIF('Screen Requirements'!$D$5:$D$134,A31) | C31: =COUNTIFS('Screen Requirements'!$D$5:$D$134,A31,'Screen Requirements'!$N$5:$N$134,"Done") | D31: =IF(B31=0,0,SUMIF('Screen Requirements'!$D$5:$D$134,A31,'Screen Requirements'!$O$5:$O$134)/B31)
A32: AI & Automation | B32: =COUNTIF('Screen Requirements'!$D$5:$D$134,A32) | C32: =COUNTIFS('Screen Requirements'!$D$5:$D$134,A32,'Screen Requirements'!$N$5:$N$134,"Done") | D32: =IF(B32=0,0,SUMIF('Screen Requirements'!$D$5:$D$134,A32,'Screen Requirements'!$O$5:$O$134)/B32)
A33: Communications | B33: =COUNTIF('Screen Requirements'!$D$5:$D$134,A33) | C33: =COUNTIFS('Screen Requirements'!$D$5:$D$134,A33,'Screen Requirements'!$N$5:$N$134,"Done") | D33: =IF(B33=0,0,SUMIF('Screen Requirements'!$D$5:$D$134,A33,'Screen Requirements'!$O$5:$O$134)/B33)
... A37: Integrations | B37: =COUNTIF('Screen Requirements'!$D$5:$D$134,A37) | C37: =COUNTIFS('Screen Requirements'!$D$5:$D$134,A37,'Screen Requirements'!$N$5:$N$134,"Done") | D37: =IF(B37=0,0,SUMIF('Screen Requirements'!$D$5:$D$134,A37,'Screen Requirements'!$O$5:$O$134)/B37)
A40: Priority-Based User Story Backlog
A41: Priority | B41: Stories | C41: Story Points | D41: Completed | E41: Progress
A42: Must Have | B42: =COUNTIF('User Stories & Acceptance'!$T$5:$T$394,A42) | C42: =SUMIF('User Stories & Acceptance'!$T$5:$T$394,A42,'User Stories & Acceptance'!$V$5:$V$394) | D42: =COUNTIFS('User Stories & Acceptance'!$T$5:$T$394,A42,'User Stories & Acceptance'!$X$5:$X$394,"Done") | E42: =IF(B42=0,0,SUMIF('User Stories & Acceptance'!$T$5:$T$394,A42,'User Stories & Acceptance'!$Y$5:$Y$394)/B42)
A43: Should Have | B43: =COUNTIF('User Stories & Acceptance'!$T$5:$T$394,A43) | C43: =SUMIF('User Stories & Acceptance'!$T$5:$T$394,A43,'User Stories & Acceptance'!$V$5:$V$394) | D43: =COUNTIFS('User Stories & Acceptance'!$T$5:$T$394,A43,'User Stories & Acceptance'!$X$5:$X$394,"Done") | E43: =IF(B43=0,0,SUMIF('User Stories & Acceptance'!$T$5:$T$394,A43,'User Stories & Acceptance'!$Y$5:$Y$394)/B43)
A44: Could Have | B44: =COUNTIF('User Stories & Acceptance'!$T$5:$T$394,A44) | C44: =SUMIF('User Stories & Acceptance'!$T$5:$T$394,A44,'User Stories & Acceptance'!$V$5:$V$394) | D44: =COUNTIFS('User Stories & Acceptance'!$T$5:$T$394,A44,'User Stories & Acceptance'!$X$5:$X$394,"Done") | E44: =IF(B44=0,0,SUMIF('User Stories & Acceptance'!$T$5:$T$394,A44,'User Stories & Acceptance'!$Y$5:$Y$394)/B44)

Sheet Module Master
A1: Module Master & Scope Overview
A3: Module ID | B3: Module | C3: Business Objective | D3: Submodules | E3: Primary Roles | F3: Core Data Entities | G3: Key Dependencies | H3: Screen Count | I3: Phase(s)
A4: MOD-01 | B4: Overview | C4: Deliver complete overview capabilities with role-based workflows, validation, auditability and cross-module synchronization. | D4: Operations Control | E4: Owner / GM / Department Heads | F4: dashboard_snapshots, operational_metrics | G4: All operational modules | H4: =COUNTIF('Screen Requirements'!$D$5:$D$134,B4) | I4: 12. Executive Dashboard, UAT & Release
A5: MOD-02 | B5: Front Desk | C5: Deliver complete front desk capabilities with role-based workflows, validation, auditability and cross-module synchronization. | D5: Room Operations, Arrival, Departure & Billing, In-Stay Movement | E5: Front Office Manager / Receptionist / Cashier | F5: stays, room_assignments, folios, keys | G5: Reservations, Rooms, Finance | H5: =COUNTIF('Screen Requirements'!$D$5:$D$134,B5) | I5: 3. Reservations, Groups & Front Desk
A6: MOD-03 | B6: Reservations | C6: Deliver complete reservations capabilities with role-based workflows, validation, auditability and cross-module synchronization. | D6: Availability & Calendar, Booking Creation, Booking Details, Booking Modification, Waitlist & Enquiry, No-Show, Data Quality, Notes & Tasks, Ancillary Sales | E6: Reservation Manager / Agent / Front Desk | F6: reservations, reservation_guests, reservation_items, deposits | G6: Rooms, Rates, Guests, Payments | H6: =COUNTIF('Screen Requirements'!$D$5:$D$134,B6) | I6: 3. Reservations, Groups & Front Desk
A7: MOD-04 | B7: Housekeeping | C7: Deliver complete housekeeping capabilities with role-based workflows, validation, auditability and cross-module synchronization. | D7: Room Operations, Task Management, Room Status, Lost Property, Laundry Operations, Minibar | E7: Housekeeping Manager / Supervisor / Attendant | F7: housekeeping_tasks, room_status_logs, lost_found, linen_movements, minibar_postings | G7: Rooms, Workforce, Inventory | H7: =COUNTIF('Screen Requirements'!$D$5:$D$134,B7) | I7: 5. Housekeeping & Guest Services
A8: MOD-05 | B8: Property & Rooms | C8: Deliver complete property & rooms capabilities with role-based workflows, validation, auditability and cross-module synchronization. | D8: Inventory, Room Details, Room Master, Room Type Master, Property Hierarchy, Amenities Master, Availability Control, Status Audit | E8: Property Admin / Front Office / Housekeeping | F8: properties, buildings, floors, room_types, rooms, amenities | G8: Administration | H8: =COUNTIF('Screen Requirements'!$D$5:$D$134,B8) | I8: 2. Inventory, Rates & Distribution Foundation | 1. Core Platform, Security & Masters
A9: MOD-06 | B9: Guest CRM | C9: Deliver complete guest crm capabilities with role-based workflows, validation, auditability and cross-module synchronization. | D9: Guest 360, Guest Directory, CRM Dashboard, Guest Master, Data Quality, Preferences & Privacy, Identity Verification, Loyalty, Privacy Operations | E9: CRM Manager / Front Desk / Reservations | F9: guests, guest_preferences, consents, documents, loyalty_accounts | G9: Reservations, Communications | H9: =COUNTIF('Screen Requirements'!$D$5:$D$134,B9) | I9: 4. Guest CRM, Privacy & Communications
A10: MOD-07 | B10: Food & Beverage | C10: Deliver complete food & beverage capabilities with role-based workflows, validation, auditability and cross-module synchronization. | D10: Kitchen, Restaurant POS, Restaurant Layout, Order Management, Billing, Controls, Menu Master, Outlet Configuration | E10: F&B Manager / Server / POS Cashier / Kitchen | F10: outlets, tables, menu_items, pos_orders, pos_bills, kitchen_tickets | G10: Inventory, Finance, Guests | H10: =COUNTIF('Screen Requirements'!$D$5:$D$134,B10) | I10: 6. Restaurant POS & Kitchen
A11: MOD-08 | B11: Guest Services | C11: Deliver complete guest services capabilities with role-based workflows, validation, auditability and cross-module synchronization. | D11: Service Desk | E11: Guest Relations / Concierge / Front Desk | F11: service_requests, service_tasks, guest_notes | G11: Guests, Rooms, Workforce | H11: =COUNTIF('Screen Requirements'!$D$5:$D$134,B11) | I11: 5. Housekeeping & Guest Services
A12: MOD-09 | B12: Activities | C12: Deliver complete activities capabilities with role-based workflows, validation, auditability and cross-module synchronization. | D12: Experience Operations, Activity Master, Bookings | E12: Activities Manager / Concierge | F12: activities, activity_slots, activity_bookings | G12: Guests, Resources, Finance | H12: =COUNTIF('Screen Requirements'!$D$5:$D$134,B12) | I12: 9. Activities, Spa, Events & Transport
A13: MOD-10 | B13: Spa | C13: Deliver complete spa capabilities with role-based workflows, validation, auditability and cross-module synchronization. | D13: Appointment Operations, Treatment Master, Resources, Appointments | E13: Spa Manager / Receptionist / Therapist | F13: treatments, spa_resources, spa_appointments | G13: Guests, Workforce, Finance | H13: =COUNTIF('Screen Requirements'!$D$5:$D$134,B13) | I13: 9. Activities, Spa, Events & Transport
A14: MOD-11 | B14: Events & Banquets | C14: Deliver complete events & banquets capabilities with role-based workflows, validation, auditability and cross-module synchronization. | D14: Event Operations, Lead Management, Quotation, Event Execution, Event Modification | E14: Sales / Event Manager / Banquet Operations | F14: event_leads, quotations, events, function_sheets | G14: Guests, Inventory, Finance | H14: =COUNTIF('Screen Requirements'!$D$5:$D$134,B14) | I14: 9. Activities, Spa, Events & Transport
A15: MOD-12 | B15: Transport | C15: Deliver complete transport capabilities with role-based workflows, validation, auditability and cross-module synchronization. | D15: Transfer Operations, Bookings, Fleet, Drivers, Trip Execution | E15: Transport Manager / Dispatcher / Driver | F15: vehicles, drivers, transport_bookings, trips | G15: Guests, Workforce, Finance | H15: =COUNTIF('Screen Requirements'!$D$5:$D$134,B15) | I15: 9. Activities, Spa, Events & Transport
... A31: MOD-28 | B31: Integrations | C31: Deliver complete integrations capabilities with role-based workflows, validation, auditability and cross-module synchronization. | D31: Integration Management | E31: Integration Admin / System Admin | F31: integrations, credentials, webhooks, sync_jobs | G31: All connected services | H31: =COUNTIF('Screen Requirements'!$D$5:$D$134,B31) | I31: 11. Portals, Integrations & AI

Sheet Screen Requirements
A1: Chirala Bay Resort PMS — Screen Requirements & Development Tracker
A2: Editable tracking columns: Development Status, Owner, Planned Start, Planned End and Remarks. Progress updates automatically.
A4: Build Order | B4: Screen ID | C4: Design Status | D4: Module | E4: Submodule | F4: Screen Name | G4: Business Purpose | H4: Functional Requirements | I4: Operations / Actions | J4: Primary Roles | K4: Priority | L4: Development Phase | M4: Sprint | N4: Development Status | O4: Progress % | P4: Dependencies | Q4: Frontend Deliverables | R4: Backend / API | S4: Data Entities | T4: Validation & Business Rules | U4: Acceptance Criteria | V4: Security & Audit | W4: Owner | X4: Planned Start | Y4: Planned End | Z4: Remarks
A5: 130 | B5: SCR-001 | C5: Completed | D5: Overview | E5: Operations Control | F5: Operations Dashboard | G5: Enable overview users to manage operations control through the Operations Dashboard workflow with real-time status, validations and traceability. | H5: Provide role-aware view, filter, search, drill down, export, refresh; support search and filters; validate mandatory fields and business conflicts; persist changes atomically; refresh related availability, balances or task status; record user, timestamp and reason for sensitive changes. | I5: View, filter, search, drill down, export, refresh | J5: Owner / GM / Department Heads | K5: Must Have | L5: 12. Executive Dashboard, UAT & Release | M5: S26-S27 | N5: Not Started | O5: =IF(N5="Done",1,IF(N5="QA",0.9,IF(N5="Integration",0.75,IF(N5="Frontend",0.55,IF(N5="Backend",0.35,IF(N5="UX/UI",0.1,0)))))) | P5: All operational modules | Q5: Responsive desktop/tablet UI; loading, empty, error and permission states; filters; form validation; accessible interactions | R5: GET, POST/PATCH /api/v1/operations-dashboard; lookup, validation and audit endpoints; idempotency for financial/booking writes | S5: dashboard_snapshots, operational_metrics | T5: Tenant/property scope; required fields; optimistic locking; timezone-safe dates; reason mandatory for overrides; valid status transition; linked-record integrity | U5: Authorized users can complete the primary operations dashboard workflow; invalid or conflicting actions are blocked with clear messages; saved changes appear in related screens; sensitive changes are auditable. | V5: RBAC, tenant and property isolation, server-side authorization, audit event for create/update/delete/override
A6: 27 | B6: SCR-002 | C6: Completed | D6: Front Desk | E6: Room Operations | F6: Room Rack | G6: Enable front desk users to manage room operations through the Room Rack workflow with real-time status, validations and traceability. | H6: Provide role-aware list, search, filter, view, create, edit, cancel/delete where allowed, export, audit; support search and filters; validate mandatory fields and business conflicts; persist changes atomically; refresh related availability, balances or task status; record user, timestamp and reason for sensitive changes. | I6: List, search, filter, view, create, edit, cancel/delete where allowed, export, audit | J6: Front Office Manager / Receptionist / Cashier | K6: Must Have | L6: 3. Reservations, Groups & Front Desk | M6: S05-S07 | N6: Not Started | O6: =IF(N6="Done",1,IF(N6="QA",0.9,IF(N6="Integration",0.75,IF(N6="Frontend",0.55,IF(N6="Backend",0.35,IF(N6="UX/UI",0.1,0)))))) | P6: Reservations, Rooms, Finance | Q6: Responsive desktop/tablet UI; loading, empty, error and permission states; filters; form validation; accessible interactions | R6: GET, POST, PUT/PATCH, DELETE /api/v1/room-rack; lookup, validation and audit endpoints; idempotency for financial/booking writes | S6: stays, room_assignments, folios, keys | T6: Tenant/property scope; required fields; optimistic locking; timezone-safe dates; reason mandatory for overrides; availability and overlap check; status-transition rules; cancellation policy | U6: Authorized users can complete the primary room rack workflow; invalid or conflicting actions are blocked with clear messages; saved changes appear in related screens; sensitive changes are auditable. | V6: RBAC, tenant and property isolation, server-side authorization, audit event for create/update/delete/override
A7: 28 | B7: SCR-003 | C7: Completed | D7: Reservations | E7: Availability & Calendar | F7: Reservation Calendar | G7: Enable reservations users to manage availability & calendar through the Reservation Calendar workflow with real-time status, validations and traceability. | H7: Provide role-aware view timeline, filter, create, assign, reschedule, conflict-check, cancel; support search and filters; validate mandatory fields and business conflicts; persist changes atomically; refresh related availability, balances or task status; record user, timestamp and reason for sensitive changes. | I7: View timeline, filter, create, assign, reschedule, conflict-check, cancel | J7: Reservation Manager / Agent / Front Desk | K7: Must Have | L7: 3. Reservations, Groups & Front Desk | M7: S05-S07 | N7: Not Started | O7: =IF(N7="Done",1,IF(N7="QA",0.9,IF(N7="Integration",0.75,IF(N7="Frontend",0.55,IF(N7="Backend",0.35,IF(N7="UX/UI",0.1,0)))))) | P7: Rooms, Rates, Guests, Payments | Q7: Responsive desktop/tablet UI; loading, empty, error and permission states; filters; form validation; accessible interactions | R7: GET, POST, PUT/PATCH, DELETE /api/v1/reservation-calendar; lookup, validation and audit endpoints; idempotency for financial/booking writes | S7: reservations, reservation_guests, reservation_items, deposits | T7: Tenant/property scope; required fields; optimistic locking; timezone-safe dates; reason mandatory for overrides; availability and overlap check; status-transition rules; cancellation policy | U7: Authorized users can complete the primary reservation calendar workflow; invalid or conflicting actions are blocked with clear messages; saved changes appear in related screens; sensitive changes are auditable. | V7: RBAC, tenant and property isolation, server-side authorization, audit event for create/update/delete/override
A8: 29 | B8: SCR-004 | C8: Completed | D8: Reservations | E8: Booking Creation | F8: New Reservation | G8: Enable reservations users to manage booking creation through the New Reservation workflow with real-time status, validations and traceability. | H8: Provide role-aware list, search, filter, view, create, edit, cancel/delete where allowed, export, audit; support search and filters; validate mandatory fields and business conflicts; persist changes atomically; refresh related availability, balances or task status; record user, timestamp and reason for sensitive changes. | I8: List, search, filter, view, create, edit, cancel/delete where allowed, export, audit | J8: Reservation Manager / Agent / Front Desk | K8: Must Have | L8: 3. Reservations, Groups & Front Desk | M8: S05-S07 | N8: Not Started | O8: =IF(N8="Done",1,IF(N8="QA",0.9,IF(N8="Integration",0.75,IF(N8="Frontend",0.55,IF(N8="Backend",0.35,IF(N8="UX/UI",0.1,0)))))) | P8: Rooms, Rates, Guests, Payments | Q8: Responsive desktop/tablet UI; loading, empty, error and permission states; filters; form validation; accessible interactions | R8: GET, POST, PUT/PATCH, DELETE /api/v1/new-reservation; lookup, validation and audit endpoints; idempotency for financial/booking writes | S8: reservations, reservation_guests, reservation_items, deposits | T8: Tenant/property scope; required fields; optimistic locking; timezone-safe dates; reason mandatory for overrides; availability and overlap check; status-transition rules; cancellation policy | U8: Authorized users can complete the primary new reservation workflow; invalid or conflicting actions are blocked with clear messages; saved changes appear in related screens; sensitive changes are auditable. | V8: RBAC, tenant and property isolation, server-side authorization, audit event for create/update/delete/override
A9: 30 | B9: SCR-005 | C9: Completed | D9: Front Desk | E9: Arrival | F9: Guest Check-In | G9: Enable front desk users to manage arrival through the Guest Check-In workflow with real-time status, validations and traceability. | H9: Provide role-aware list, search, filter, view, create, edit, cancel/delete where allowed, export, audit; support search and filters; validate mandatory fields and business conflicts; persist changes atomically; refresh related availability, balances or task status; record user, timestamp and reason for sensitive changes. | I9: List, search, filter, view, create, edit, cancel/delete where allowed, export, audit | J9: Front Office Manager / Receptionist / Cashier | K9: Must Have | L9: 3. Reservations, Groups & Front Desk | M9: S05-S07 | N9: Not Started | O9: =IF(N9="Done",1,IF(N9="QA",0.9,IF(N9="Integration",0.75,IF(N9="Frontend",0.55,IF(N9="Backend",0.35,IF(N9="UX/UI",0.1,0)))))) | P9: Reservations, Rooms, Finance | Q9: Responsive desktop/tablet UI; loading, empty, error and permission states; filters; form validation; accessible interactions | R9: GET, POST, PUT/PATCH, DELETE /api/v1/guest-check-in; lookup, validation and audit endpoints; idempotency for financial/booking writes | S9: stays, room_assignments, folios, keys | T9: Tenant/property scope; required fields; optimistic locking; timezone-safe dates; reason mandatory for overrides; availability and overlap check; status-transition rules; cancellation policy | U9: Authorized users can complete the primary guest check-in workflow; invalid or conflicting actions are blocked with clear messages; saved changes appear in related screens; sensitive changes are auditable. | V9: RBAC, tenant and property isolation, server-side authorization, audit event for create/update/delete/override
A10: 59 | B10: SCR-006 | C10: Completed | D10: Housekeeping | E10: Room Operations | F10: Housekeeping Operations | G10: Enable housekeeping users to manage room operations through the Housekeeping Operations workflow with real-time status, validations and traceability. | H10: Provide role-aware list, search, filter, view, create, edit, cancel/delete where allowed, export, audit; support search and filters; validate mandatory fields and business conflicts; persist changes atomically; refresh related availability, balances or task status; record user, timestamp and reason for sensitive changes. | I10: List, search, filter, view, create, edit, cancel/delete where allowed, export, audit | J10: Housekeeping Manager / Supervisor / Attendant | K10: Should Have | L10: 5. Housekeeping & Guest Services | M10: S10-S11 | N10: Not Started | O10: =IF(N10="Done",1,IF(N10="QA",0.9,IF(N10="Integration",0.75,IF(N10="Frontend",0.55,IF(N10="Backend",0.35,IF(N10="UX/UI",0.1,0)))))) | P10: Rooms, Workforce, Inventory | Q10: Responsive desktop/tablet UI; loading, empty, error and permission states; filters; form validation; accessible interactions | R10: GET, POST, PUT/PATCH, DELETE /api/v1/housekeeping-operations; lookup, validation and audit endpoints; idempotency for financial/booking writes | S10: housekeeping_tasks, room_status_logs, lost_found, linen_movements, minibar_postings | T10: Tenant/property scope; required fields; optimistic locking; timezone-safe dates; reason mandatory for overrides; valid status transition; linked-record integrity | U10: Authorized users can complete the primary housekeeping operations workflow; invalid or conflicting actions are blocked with clear messages; saved changes appear in related screens; sensitive changes are auditable. | V10: RBAC, tenant and property isolation, server-side authorization, audit event for create/update/delete/override
A11: 31 | B11: SCR-007 | C11: Completed | D11: Front Desk | E11: Departure & Billing | F11: Guest Checkout Folio | G11: Enable front desk users to manage departure & billing through the Guest Checkout Folio workflow with real-time status, validations and traceability. | H11: Provide role-aware list, search, filter, view, create, edit, cancel/delete where allowed, export, audit; support search and filters; validate mandatory fields and business conflicts; persist changes atomically; refresh related availability, balances or task status; record user, timestamp and reason for sensitive changes. | I11: List, search, filter, view, create, edit, cancel/delete where allowed, export, audit | J11: Front Office Manager / Receptionist / Cashier | K11: Must Have | L11: 3. Reservations, Groups & Front Desk | M11: S05-S07 | N11: Not Started | O11: =IF(N11="Done",1,IF(N11="QA",0.9,IF(N11="Integration",0.75,IF(N11="Frontend",0.55,IF(N11="Backend",0.35,IF(N11="UX/UI",0.1,0)))))) | P11: Reservations, Rooms, Finance | Q11: Responsive desktop/tablet UI; loading, empty, error and permission states; filters; form validation; accessible interactions | R11: GET, POST, PUT/PATCH, DELETE /api/v1/guest-checkout-folio; lookup, validation and audit endpoints; idempotency for financial/booking writes | S11: stays, room_assignments, folios, keys | T11: Tenant/property scope; required fields; optimistic locking; timezone-safe dates; reason mandatory for overrides; availability and overlap check; status-transition rules; cancellation policy | U11: Authorized users can complete the primary guest checkout folio workflow; invalid or conflicting actions are blocked with clear messages; saved changes appear in related screens; sensitive changes are auditable. | V11: RBAC, tenant and property isolation, server-side authorization, audit event for create/update/delete/override
A12: 16 | B12: SCR-008 | C12: Completed | D12: Property & Rooms | E12: Inventory | F12: Rooms and Villas Inventory | G12: Enable property & rooms users to manage inventory through the Rooms and Villas Inventory workflow with real-time status, validations and traceability. | H12: Provide role-aware list, search, filter, view, create, edit, cancel/delete where allowed, export, audit; support search and filters; validate mandatory fields and business conflicts; persist changes atomically; refresh related availability, balances or task status; record user, timestamp and reason for sensitive changes. | I12: List, search, filter, view, create, edit, cancel/delete where allowed, export, audit | J12: Property Admin / Front Office / Housekeeping | K12: Must Have | L12: 2. Inventory, Rates & Distribution Foundation | M12: S03-S04 | N12: Not Started | O12: =IF(N12="Done",1,IF(N12="QA",0.9,IF(N12="Integration",0.75,IF(N12="Frontend",0.55,IF(N12="Backend",0.35,IF(N12="UX/UI",0.1,0)))))) | P12: Administration | Q12: Responsive desktop/tablet UI; loading, empty, error and permission states; filters; form validation; accessible interactions | R12: GET, POST, PUT/PATCH, DELETE /api/v1/rooms-and-villas-inventory; lookup, validation and audit endpoints; idempotency for financial/booking writes | S12: properties, buildings, floors, room_types, rooms, amenities | T12: Tenant/property scope; required fields; optimistic locking; timezone-safe dates; reason mandatory for overrides; valid status transition; linked-record integrity | U12: Authorized users can complete the primary rooms and villas inventory workflow; invalid or conflicting actions are blocked with clear messages; saved changes appear in related screens; sensitive changes are auditable. | V12: RBAC, tenant and property isolation, server-side authorization, audit event for create/update/delete/override
A13: 48 | B13: SCR-009 | C13: Completed | D13: Guest CRM | E13: Guest 360 | F13: Guest Profile | G13: Enable guest crm users to manage guest 360 through the Guest Profile workflow with real-time status, validations and traceability. | H13: Provide role-aware list, search, filter, view, create, edit, cancel/delete where allowed, export, audit; support search and filters; validate mandatory fields and business conflicts; persist changes atomically; refresh related availability, balances or task status; record user, timestamp and reason for sensitive changes. | I13: List, search, filter, view, create, edit, cancel/delete where allowed, export, audit | J13: CRM Manager / Front Desk / Reservations | K13: Should Have | L13: 4. Guest CRM, Privacy & Communications | M13: S08-S09 | N13: Not Started | O13: =IF(N13="Done",1,IF(N13="QA",0.9,IF(N13="Integration",0.75,IF(N13="Frontend",0.55,IF(N13="Backend",0.35,IF(N13="UX/UI",0.1,0)))))) | P13: Reservations, Communications | Q13: Responsive desktop/tablet UI; loading, empty, error and permission states; filters; form validation; accessible interactions | R13: GET, POST, PUT/PATCH, DELETE /api/v1/guest-profile; lookup, validation and audit endpoints; idempotency for financial/booking writes | S13: guests, guest_preferences, consents, documents, loyalty_accounts | T13: Tenant/property scope; required fields; optimistic locking; timezone-safe dates; reason mandatory for overrides; duplicate detection; consent and retention policy; sensitive document masking | U13: Authorized users can complete the primary guest profile workflow; invalid or conflicting actions are blocked with clear messages; saved changes appear in related screens; sensitive changes are auditable. | V13: RBAC, tenant and property isolation, server-side authorization, audit event for create/update/delete/override; field masking and approval/audit evidence required
A14: 49 | B14: SCR-010 | C14: Completed | D14: Guest CRM | E14: Guest Directory | F14: Guest Directory | G14: Enable guest crm users to manage guest directory through the Guest Directory workflow with real-time status, validations and traceability. | H14: Provide role-aware list, search, filter, view, create, edit, cancel/delete where allowed, export, audit; support search and filters; validate mandatory fields and business conflicts; persist changes atomically; refresh related availability, balances or task status; record user, timestamp and reason for sensitive changes. | I14: List, search, filter, view, create, edit, cancel/delete where allowed, export, audit | J14: CRM Manager / Front Desk / Reservations | K14: Should Have | L14: 4. Guest CRM, Privacy & Communications | M14: S08-S09 | N14: Not Started | O14: =IF(N14="Done",1,IF(N14="QA",0.9,IF(N14="Integration",0.75,IF(N14="Frontend",0.55,IF(N14="Backend",0.35,IF(N14="UX/UI",0.1,0)))))) | P14: Reservations, Communications | Q14: Responsive desktop/tablet UI; loading, empty, error and permission states; filters; form validation; accessible interactions | R14: GET, POST, PUT/PATCH, DELETE /api/v1/guest-directory; lookup, validation and audit endpoints; idempotency for financial/booking writes | S14: guests, guest_preferences, consents, documents, loyalty_accounts | T14: Tenant/property scope; required fields; optimistic locking; timezone-safe dates; reason mandatory for overrides; duplicate detection; consent and retention policy; sensitive document masking | U14: Authorized users can complete the primary guest directory workflow; invalid or conflicting actions are blocked with clear messages; saved changes appear in related screens; sensitive changes are auditable. | V14: RBAC, tenant and property isolation, server-side authorization, audit event for create/update/delete/override; field masking and approval/audit evidence required
A15: 17 | B15: SCR-011 | C15: Completed | D15: Property & Rooms | E15: Room Details | F15: Room Details | G15: Enable property & rooms users to manage room details through the Room Details workflow with real-time status, validations and traceability. | H15: Provide role-aware list, search, filter, view, create, edit, cancel/delete where allowed, export, audit; support search and filters; validate mandatory fields and business conflicts; persist changes atomically; refresh related availability, balances or task status; record user, timestamp and reason for sensitive changes. | I15: List, search, filter, view, create, edit, cancel/delete where allowed, export, audit | J15: Property Admin / Front Office / Housekeeping | K15: Must Have | L15: 2. Inventory, Rates & Distribution Foundation | M15: S03-S04 | N15: Not Started | O15: =IF(N15="Done",1,IF(N15="QA",0.9,IF(N15="Integration",0.75,IF(N15="Frontend",0.55,IF(N15="Backend",0.35,IF(N15="UX/UI",0.1,0)))))) | P15: Administration | Q15: Responsive desktop/tablet UI; loading, empty, error and permission states; filters; form validation; accessible interactions | R15: GET, POST, PUT/PATCH, DELETE /api/v1/room-details; lookup, validation and audit endpoints; idempotency for financial/booking writes | S15: properties, buildings, floors, room_types, rooms, amenities | T15: Tenant/property scope; required fields; optimistic locking; timezone-safe dates; reason mandatory for overrides; valid status transition; linked-record integrity | U15: Authorized users can complete the primary room details workflow; invalid or conflicting actions are blocked with clear messages; saved changes appear in related screens; sensitive changes are auditable. | V15: RBAC, tenant and property isolation, server-side authorization, audit event for create/update/delete/override
A16: 67 | B16: SCR-012 | C16: Completed | D16: Food & Beverage | E16: Kitchen | F16: Kitchen Display System | G16: Enable food & beverage users to manage kitchen through the Kitchen Display System workflow with real-time status, validations and traceability. | H16: Provide role-aware list, search, filter, view, create, edit, cancel/delete where allowed, export, audit; support search and filters; validate mandatory fields and business conflicts; persist changes atomically; refresh related availability, balances or task status; record user, timestamp and reason for sensitive changes. | I16: List, search, filter, view, create, edit, cancel/delete where allowed, export, audit | J16: F&B Manager / Server / POS Cashier / Kitchen | K16: Should Have | L16: 6. Restaurant POS & Kitchen | M16: S12-S13 | N16: Not Started | O16: =IF(N16="Done",1,IF(N16="QA",0.9,IF(N16="Integration",0.75,IF(N16="Frontend",0.55,IF(N16="Backend",0.35,IF(N16="UX/UI",0.1,0)))))) | P16: Inventory, Finance, Guests | Q16: Responsive desktop/tablet UI; loading, empty, error and permission states; filters; form validation; accessible interactions | R16: GET, POST, PUT/PATCH, DELETE /api/v1/kitchen-display-system; lookup, validation and audit endpoints; idempotency for financial/booking writes | S16: outlets, tables, menu_items, pos_orders, pos_bills, kitchen_tickets | T16: Tenant/property scope; required fields; optimistic locking; timezone-safe dates; reason mandatory for overrides; currency precision; tax/rate totals; approval limit; no unbalanced or duplicate posting | U16: Authorized users can complete the primary kitchen display system workflow; invalid or conflicting actions are blocked with clear messages; saved changes appear in related screens; sensitive changes are auditable. | V16: RBAC, tenant and property isolation, server-side authorization, audit event for create/update/delete/override
... A134: 129 | B134: SCR-130 | C134: Pending | D134: Partner Portal | E134: Portal Operations | F134: Portal Booking Management | G134: Enable partner portal users to manage portal operations through the Portal Booking Management workflow with real-time status, validations and traceability. | H134: Provide role-aware list, view, create, edit, activate/deactivate, delete where safe, audit; support search and filters; validate mandatory fields and business conflicts; persist changes atomically; refresh related availability, balances or task status; record user, timestamp and reason for sensitive changes. | I134: List, view, create, edit, activate/deactivate, delete where safe, audit | J134: Travel Agent / Corporate Booker / Sales | K134: Could Have | L134: 11. Portals, Integrations & AI | M134: S23-S25 | N134: Not Started | O134: =IF(N134="Done",1,IF(N134="QA",0.9,IF(N134="Integration",0.75,IF(N134="Frontend",0.55,IF(N134="Backend",0.35,IF(N134="UX/UI",0.1,0)))))) | P134: Reservations, Rates, Finance | Q134: Responsive desktop/tablet UI; loading, empty, error and permission states; filters; form validation; accessible interactions | R134: GET, POST, PUT/PATCH, DELETE /api/v1/portal-booking-management; lookup, validation and audit endpoints; idempotency for financial/booking writes | S134: partner_accounts, portal_bookings, commissions | T134: Tenant/property scope; required fields; optimistic locking; timezone-safe dates; reason mandatory for overrides; valid status transition; linked-record integrity | U134: Authorized users can complete the primary portal booking management workflow; invalid or conflicting actions are blocked with clear messages; saved changes appear in related screens; sensitive changes are auditable. | V134: RBAC, tenant and property isolation, server-side authorization, audit event for create/update/delete/override

Sheet Development Plan
A1: Sequence-Wise Development Plan
A2: Suggested baseline: 1 product owner, 1 UX/UI, 2 frontend, 2 backend, 1 QA, shared DevOps. Dates may be changed after team capacity is confirmed.
A4: Phase | B4: Phase Name | C4: Sprint(s) | D4: Planned Start | E4: Planned End | F4: Duration (Weeks) | G4: Screen Count | H4: Screen IDs | I4: Prerequisite | J4: Main Deliverables | K4: Exit Criteria | L4: Phase Status | M4: Progress %
A5: 1 | B5: Core Platform, Security & Masters | C5: S01-S02 | D5: 46272 | E5: 46299 | F5: 4 | G5: 15 | H5: SCR-026, SCR-039, SCR-040, SCR-041, SCR-042, SCR-043, SCR-059, SCR-060, SCR-061, SCR-062, SCR-063, SCR-064, SCR-123, SCR-125, SCR-126 | I5: Approved architecture, environments and design system | J5: Implement, integrate and test core platform, security & masters screens, APIs, entities, permissions, audit events and reports. | K5: Tenant-safe authentication, RBAC, audit and property masters pass integration tests | L5: Not Started | M5: =IF(L5="Done",1,IF(L5="QA",0.9,IF(L5="Integration",0.75,IF(L5="Frontend",0.55,IF(L5="Backend",0.35,IF(L5="UX/UI",0.1,0))))))
A6: 2 | B6: Inventory, Rates & Distribution Foundation | C6: S03-S04 | D6: 46300 | E6: 46327 | F6: 4 | G6: 11 | H6: SCR-008, SCR-011, SCR-024, SCR-033, SCR-034, SCR-035, SCR-058, SCR-118, SCR-119, SCR-120, SCR-121 | I6: Phase 1 property and permission masters | J6: Implement, integrate and test inventory, rates & distribution foundation screens, APIs, entities, permissions, audit events and reports. | K6: Sellable inventory, rate calculations and restriction rules reconcile | L6: Not Started | M6: =IF(L6="Done",1,IF(L6="QA",0.9,IF(L6="Integration",0.75,IF(L6="Frontend",0.55,IF(L6="Backend",0.35,IF(L6="UX/UI",0.1,0))))))
A7: 3 | B7: Reservations, Groups & Front Desk | C7: S05-S07 | D7: 46328 | E7: 46369 | F7: 6 | G7: 21 | H7: SCR-002, SCR-003, SCR-004, SCR-005, SCR-007, SCR-028, SCR-029, SCR-030, SCR-031, SCR-032, SCR-051, SCR-052, SCR-053, SCR-054, SCR-055, SCR-056, SCR-057, SCR-114, SCR-115, SCR-116, SCR-117 | I7: Availability, rates, taxes and room masters | J7: Implement, integrate and test reservations, groups & front desk screens, APIs, entities, permissions, audit events and reports. | K7: End-to-end book, modify, arrive, in-stay, settle and depart flow passes | L7: Not Started | M7: =IF(L7="Done",1,IF(L7="QA",0.9,IF(L7="Integration",0.75,IF(L7="Frontend",0.55,IF(L7="Backend",0.35,IF(L7="UX/UI",0.1,0))))))
A8: 4 | B8: Guest CRM, Privacy & Communications | C8: S08-S09 | D8: 46370 | E8: 46397 | F8: 4 | G8: 11 | H8: SCR-009, SCR-010, SCR-025, SCR-047, SCR-065, SCR-066, SCR-067, SCR-068, SCR-069, SCR-070, SCR-122 | I8: Guest and reservation identities from Phase 3 | J8: Implement, integrate and test guest crm, privacy & communications screens, APIs, entities, permissions, audit events and reports. | K8: Guest 360, consent, KYC, dedupe and communication journeys pass | L8: Not Started | M8: =IF(L8="Done",1,IF(L8="QA",0.9,IF(L8="Integration",0.75,IF(L8="Frontend",0.55,IF(L8="Backend",0.35,IF(L8="UX/UI",0.1,0))))))
A9: 5 | B9: Housekeeping & Guest Services | C9: S10-S11 | D9: 46398 | E9: 46425 | F9: 4 | G9: 8 | H9: SCR-006, SCR-014, SCR-071, SCR-072, SCR-073, SCR-074, SCR-075, SCR-076 | I9: Rooms, guests and in-house stays | J9: Implement, integrate and test housekeeping & guest services screens, APIs, entities, permissions, audit events and reports. | K9: Room turnaround, service tasks and minibar postings synchronize | L9: Not Started | M9: =IF(L9="Done",1,IF(L9="QA",0.9,IF(L9="Integration",0.75,IF(L9="Frontend",0.55,IF(L9="Backend",0.35,IF(L9="UX/UI",0.1,0))))))
A10: 6 | B10: Restaurant POS & Kitchen | C10: S12-S13 | D10: 46426 | E10: 46453 | F10: 4 | G10: 9 | H10: SCR-012, SCR-013, SCR-077, SCR-078, SCR-079, SCR-080, SCR-081, SCR-082, SCR-083 | I10: Tax, payment, outlets and inventory masters | J10: Implement, integrate and test restaurant pos & kitchen screens, APIs, entities, permissions, audit events and reports. | K10: Order-to-kitchen-to-bill flow and approvals pass | L10: Not Started | M10: =IF(L10="Done",1,IF(L10="QA",0.9,IF(L10="Integration",0.75,IF(L10="Frontend",0.55,IF(L10="Backend",0.35,IF(L10="UX/UI",0.1,0))))))
A11: 7 | B11: Inventory & Procurement | C11: S14-S15 | D11: 46454 | E11: 46481 | F11: 4 | G11: 10 | H11: SCR-020, SCR-023, SCR-102, SCR-103, SCR-104, SCR-105, SCR-106, SCR-107, SCR-108, SCR-109 | I11: Property, finance and user approval setup | J11: Implement, integrate and test inventory & procurement screens, APIs, entities, permissions, audit events and reports. | K11: Requisition-to-PO-to-receipt-to-stock and return flow reconciles | L11: Not Started | M11: =IF(L11="Done",1,IF(L11="QA",0.9,IF(L11="Integration",0.75,IF(L11="Frontend",0.55,IF(L11="Backend",0.35,IF(L11="UX/UI",0.1,0))))))
A12: 8 | B12: Maintenance & Asset Operations | C12: S16 | D12: 46482 | E12: 46495 | F12: 2 | G12: 6 | H12: SCR-019, SCR-097, SCR-098, SCR-099, SCR-100, SCR-101 | I12: Property locations, users and inventory items | J12: Implement, integrate and test maintenance & asset operations screens, APIs, entities, permissions, audit events and reports. | K12: Corrective and preventive work orders update assets and costs | L12: Not Started | M12: =IF(L12="Done",1,IF(L12="QA",0.9,IF(L12="Integration",0.75,IF(L12="Frontend",0.55,IF(L12="Backend",0.35,IF(L12="UX/UI",0.1,0))))))
A13: 9 | B13: Activities, Spa, Events & Transport | C13: S17-S19 | D13: 46496 | E13: 46537 | F13: 6 | G13: 17 | H13: SCR-015, SCR-016, SCR-017, SCR-018, SCR-084, SCR-085, SCR-086, SCR-087, SCR-088, SCR-089, SCR-090, SCR-091, SCR-092, SCR-093, SCR-094, SCR-095, SCR-096 | I13: Guests, payments, resources and notifications | J13: Implement, integrate and test activities, spa, events & transport screens, APIs, entities, permissions, audit events and reports. | K13: Resource-safe booking, service delivery and settlement pass for all outlets | L13: Not Started | M13: =IF(L13="Done",1,IF(L13="QA",0.9,IF(L13="Integration",0.75,IF(L13="Frontend",0.55,IF(L13="Backend",0.35,IF(L13="UX/UI",0.1,0))))))
A14: 10 | B14: Workforce, Finance & Analytics | C14: S20-S22 | D14: 46538 | E14: 46579 | F14: 6 | G14: 10 | H14: SCR-021, SCR-022, SCR-027, SCR-036, SCR-037, SCR-038, SCR-110, SCR-111, SCR-112, SCR-113 | I14: Operational postings and approval hierarchy | J14: Implement, integrate and test workforce, finance & analytics screens, APIs, entities, permissions, audit events and reports. | K14: Roster, attendance, cashiering, audit close, AR and reports reconcile | L14: Not Started | M14: =IF(L14="Done",1,IF(L14="QA",0.9,IF(L14="Integration",0.75,IF(L14="Frontend",0.55,IF(L14="Backend",0.35,IF(L14="UX/UI",0.1,0))))))
A15: 11 | B15: Portals, Integrations & AI | C15: S23-S25 | D15: 46580 | E15: 46621 | F15: 6 | G15: 11 | H15: SCR-044, SCR-045, SCR-046, SCR-048, SCR-049, SCR-050, SCR-124, SCR-127, SCR-128, SCR-129, SCR-130 | I15: Stable APIs, permissions, notification and knowledge policies | J15: Implement, integrate and test portals, integrations & ai screens, APIs, entities, permissions, audit events and reports. | K15: Portal, integration and AI tool calls are secure, observable and accepted | L15: Not Started | M15: =IF(L15="Done",1,IF(L15="QA",0.9,IF(L15="Integration",0.75,IF(L15="Frontend",0.55,IF(L15="Backend",0.35,IF(L15="UX/UI",0.1,0))))))
A16: 12 | B16: Executive Dashboard, UAT & Release | C16: S26-S27 | D16: 46622 | E16: 46649 | F16: 4 | G16: 1 | H16: SCR-001 | I16: All operational modules integrated in staging | J16: Implement, integrate and test executive dashboard, uat & release screens, APIs, entities, permissions, audit events and reports. | K16: KPI reconciliation, security, performance, migration, training and go-live sign-off | L16: Not Started | M16: =IF(L16="Done",1,IF(L16="QA",0.9,IF(L16="Integration",0.75,IF(L16="Frontend",0.55,IF(L16="Backend",0.35,IF(L16="UX/UI",0.1,0))))))

Sheet Role Access Matrix
A1: Role Access Matrix by Module
A2: Permissions: V View, C Create, E Edit, D Delete/Deactivate, A Approve/Override, S Self-service, X No access. Enforce server-side; UI visibility is not authorization.
A4: Role | B4: Overview | C4: Front Desk | D4: Reservations | E4: Housekeeping | F4: Property & Rooms | G4: Guest CRM | H4: Food & Beverage | I4: Guest Services | J4: Activities | K4: Spa | L4: Events & Banquets | M4: Transport | N4: Maintenance | O4: Inventory | P4: Workforce | Q4: Finance | R4: Purchasing | S4: Distribution | T4: Administration | U4: Analytics | V4: Groups | W4: Revenue Management | X4: AI & Automation | Y4: Communications | Z4: Guest Portal | AA4: Partner Portal | AB4: Sales & Marketing | AC4: Integrations
A5: Owner / General Manager | B5: V,A | C5: V,A | D5: V,A | E5: V,A | F5: V,A | G5: V,A | H5: V,A | I5: V,A | J5: V,A | K5: V,A | L5: V,A | M5: V,A | N5: V,A | O5: V,A | P5: V,A | Q5: V,A | R5: V,A | S5: V,A | T5: V,A | U5: V,A | V5: V,A | W5: V,A | X5: V,A | Y5: V,A | Z5: V,A | AA5: V,A | AB5: V,A | AC5: V,A
A6: System Administrator | B6: V | C6: V | D6: V | E6: V | F6: V | G6: V | H6: V | I6: V | J6: V | K6: V | L6: V | M6: V | N6: V | O6: V | P6: V | Q6: V | R6: V | S6: V | T6: V,C,E,D,A | U6: V | V6: V | W6: V | X6: V,C,E,D,A | Y6: V | Z6: V | AA6: V | AB6: V | AC6: V,C,E,D,A
A7: Property Administrator | B7: V | C7: V | D7: V | E7: V | F7: V,C,E,D,A | G7: V | H7: V | I7: V | J7: V | K7: V | L7: V | M7: V | N7: V | O7: V | P7: V | Q7: V | R7: V | S7: V | T7: V,C,E,D,A | U7: V | V7: V | W7: V | X7: V | Y7: V | Z7: V | AA7: V | AB7: V | AC7: V
A8: Front Office Manager | B8: V | C8: V,C,E,D,A | D8: V,C,E,D,A | E8: X | F8: V,C,E,D,A | G8: V,C,E,D,A | H8: X | I8: V,C,E,D,A | J8: X | K8: X | L8: X | M8: X | N8: X | O8: X | P8: X | Q8: V,C,E,D,A | R8: X | S8: X | T8: X | U8: V | V8: V,C,E,D,A | W8: X | X8: X | Y8: X | Z8: X | AA8: X | AB8: X | AC8: X
A9: Receptionist | B9: V | C9: V,C,E,D,A | D9: V,C,E,D,A | E9: X | F9: X | G9: V,C,E,D,A | H9: X | I9: V,C,E,D,A | J9: V,C,E,D,A | K9: V,C,E,D,A | L9: X | M9: V,C,E,D,A | N9: X | O9: X | P9: X | Q9: V,C,E,D,A | R9: X | S9: X | T9: X | U9: V | V9: X | W9: X | X9: X | Y9: X | Z9: X | AA9: X | AB9: X | AC9: X
A10: Reservation Manager / Agent | B10: V | C10: X | D10: V,C,E,D,A | E10: X | F10: X | G10: V,C,E,D,A | H10: X | I10: X | J10: X | K10: X | L10: X | M10: X | N10: X | O10: X | P10: X | Q10: X | R10: X | S10: V,C,E,D,A | T10: X | U10: V | V10: V,C,E,D,A | W10: V,C,E,D,A | X10: X | Y10: X | Z10: X | AA10: V,C,E,D,A | AB10: X | AC10: X
A11: Housekeeping Manager | B11: V | C11: X | D11: X | E11: V,C,E,D,A | F11: V,C,E,D,A | G11: X | H11: X | I11: V,C,E,D,A | J11: X | K11: X | L11: X | M11: X | N11: X | O11: V,C,E,D,A | P11: V,C,E,D,A | Q11: X | R11: X | S11: X | T11: X | U11: V | V11: X | W11: X | X11: X | Y11: X | Z11: X | AA11: X | AB11: X | AC11: X
A12: Housekeeping Attendant | B12: V | C12: X | D12: X | E12: V,C,E | F12: X | G12: X | H12: X | I12: V,C,E | J12: X | K12: X | L12: X | M12: X | N12: X | O12: X | P12: X | Q12: X | R12: X | S12: X | T12: X | U12: V | V12: X | W12: X | X12: X | Y12: X | Z12: X | AA12: X | AB12: X | AC12: X
A13: F&B Manager | B13: V | C13: X | D13: X | E13: X | F13: X | G13: X | H13: V,C,E,D,A | I13: X | J13: X | K13: X | L13: X | M13: X | N13: X | O13: V,C,E,D,A | P13: X | Q13: V,C,E,D,A | R13: V,C,E,D,A | S13: X | T13: X | U13: V,C,E,D,A | V13: X | W13: X | X13: X | Y13: X | Z13: X | AA13: X | AB13: X | AC13: X
A14: POS Cashier / Server | B14: V | C14: X | D14: X | E14: X | F14: X | G14: X | H14: V,C,E | I14: X | J14: X | K14: X | L14: X | M14: X | N14: X | O14: X | P14: X | Q14: V,C,E | R14: X | S14: X | T14: X | U14: V | V14: X | W14: X | X14: X | Y14: X | Z14: X | AA14: X | AB14: X | AC14: X
A15: Spa / Activities Manager | B15: V | C15: X | D15: X | E15: X | F15: X | G15: V,C,E,D,A | H15: X | I15: X | J15: V,C,E,D,A | K15: V,C,E,D,A | L15: X | M15: X | N15: X | O15: X | P15: V,C,E,D,A | Q15: V,C,E,D,A | R15: X | S15: X | T15: X | U15: V | V15: X | W15: X | X15: X | Y15: X | Z15: X | AA15: X | AB15: X | AC15: X
... A27: AI / Integration Admin | B27: V | C27: X | D27: X | E27: X | F27: X | G27: X | H27: X | I27: X | J27: X | K27: X | L27: X | M27: X | N27: X | O27: X | P27: X | Q27: X | R27: X | S27: X | T27: V,C,E,D,A | U27: V | V27: X | W27: X | X27: V,C,E,D,A | Y27: V,C,E,D,A | Z27: X | AA27: X | AB27: X | AC27: V,C,E,D,A

Sheet API & Data Mapping
A1: API, Data Entity & Integration Mapping
A3: Module | B3: Service / Bounded Context | C3: Core API Pattern | D3: Core Data Entities | E3: Domain Events | F3: External Integrations | G3: Security & Audit | H3: Implementation Status
A4: Overview | B4: Overview Service | C4: /api/v1/overview/* | D4: dashboard_snapshots, operational_metrics | E4: overview.created; overview.updated; overview.status_changed | F4: Internal event bus and notification service | G4: Tenant/property scope; RBAC; encryption; idempotency; audit correlation ID | H4: Not Started
A5: Front Desk | B5: Front Desk Service | C5: /api/v1/front-desk/* | D5: stays, room_assignments, folios, keys | E5: front-desk.created; front-desk.updated; front-desk.status_changed | F5: Internal event bus and notification service | G5: Tenant/property scope; RBAC; encryption; idempotency; audit correlation ID | H5: Not Started
A6: Reservations | B6: Reservations Service | C6: /api/v1/reservations/* | D6: reservations, reservation_guests, reservation_items, deposits | E6: reservations.created; reservations.updated; reservations.status_changed | F6: Internal event bus and notification service | G6: Tenant/property scope; RBAC; encryption; idempotency; audit correlation ID | H6: Not Started
A7: Housekeeping | B7: Housekeeping Service | C7: /api/v1/housekeeping/* | D7: housekeeping_tasks, room_status_logs, lost_found, linen_movements, minibar_postings | E7: housekeeping.created; housekeeping.updated; housekeeping.status_changed | F7: Internal event bus and notification service | G7: Tenant/property scope; RBAC; encryption; idempotency; audit correlation ID | H7: Not Started
A8: Property & Rooms | B8: Property & Rooms Service | C8: /api/v1/property-rooms/* | D8: properties, buildings, floors, room_types, rooms, amenities | E8: property-rooms.created; property-rooms.updated; property-rooms.status_changed | F8: Internal event bus and notification service | G8: Tenant/property scope; RBAC; encryption; idempotency; audit correlation ID | H8: Not Started
A9: Guest CRM | B9: Guest CRM Service | C9: /api/v1/guest-crm/* | D9: guests, guest_preferences, consents, documents, loyalty_accounts | E9: guest-crm.created; guest-crm.updated; guest-crm.status_changed | F9: Internal event bus and notification service | G9: Tenant/property scope; RBAC; encryption; idempotency; audit correlation ID | H9: Not Started
A10: Food & Beverage | B10: Food & Beverage Service | C10: /api/v1/food-beverage/* | D10: outlets, tables, menu_items, pos_orders, pos_bills, kitchen_tickets | E10: food-beverage.created; food-beverage.updated; food-beverage.status_changed | F10: Internal event bus and notification service | G10: Tenant/property scope; RBAC; encryption; idempotency; audit correlation ID | H10: Not Started
A11: Guest Services | B11: Guest Services Service | C11: /api/v1/guest-services/* | D11: service_requests, service_tasks, guest_notes | E11: guest-services.created; guest-services.updated; guest-services.status_changed | F11: Internal event bus and notification service | G11: Tenant/property scope; RBAC; encryption; idempotency; audit correlation ID | H11: Not Started
A12: Activities | B12: Activities Service | C12: /api/v1/activities/* | D12: activities, activity_slots, activity_bookings | E12: activities.created; activities.updated; activities.status_changed | F12: Internal event bus and notification service | G12: Tenant/property scope; RBAC; encryption; idempotency; audit correlation ID | H12: Not Started
A13: Spa | B13: Spa Service | C13: /api/v1/spa/* | D13: treatments, spa_resources, spa_appointments | E13: spa.created; spa.updated; spa.status_changed | F13: Internal event bus and notification service | G13: Tenant/property scope; RBAC; encryption; idempotency; audit correlation ID | H13: Not Started
A14: Events & Banquets | B14: Events & Banquets Service | C14: /api/v1/events-banquets/* | D14: event_leads, quotations, events, function_sheets | E14: events-banquets.created; events-banquets.updated; events-banquets.status_changed | F14: Internal event bus and notification service | G14: Tenant/property scope; RBAC; encryption; idempotency; audit correlation ID | H14: Not Started
... A31: Integrations | B31: Integrations Service | C31: /api/v1/integrations/* | D31: integrations, credentials, webhooks, sync_jobs | E31: integrations.created; integrations.updated; integrations.status_changed | F31: Webhooks, partner APIs and scheduled sync | G31: Tenant/property scope; RBAC; encryption; idempotency; audit correlation ID | H31: Not Started

Sheet Test & Acceptance
A1: Screen Test & Acceptance Tracker
A3: Test ID | B3: Screen ID | C3: Module | D3: Screen Name | E3: Test Scenario | F3: Precondition | G3: Test Steps | H3: Expected Result | I3: Test Type | J3: Severity | K3: Owner | L3: Status | M3: Defect / Remarks
A4: TC-001 | B4: SCR-001 | C4: Overview | D4: Operations Dashboard | E4: Complete primary Operations Dashboard workflow with valid data and verify one invalid/unauthorized path. | F4: Test property, role and dependent master data exist. | G4: 1. Sign in with authorized role. 2. Open screen. 3. Search/create/edit/process primary record. 4. Validate status and related screen. 5. Verify audit. | H4: Valid action succeeds once; invalid/conflicting action is blocked; related data is consistent; audit contains actor, timestamp and reason. | I4: Functional + RBAC + Integration | J4: Critical | L4: Not Run
A5: TC-002 | B5: SCR-002 | C5: Front Desk | D5: Room Rack | E5: Complete primary Room Rack workflow with valid data and verify one invalid/unauthorized path. | F5: Test property, role and dependent master data exist. | G5: 1. Sign in with authorized role. 2. Open screen. 3. Search/create/edit/process primary record. 4. Validate status and related screen. 5. Verify audit. | H5: Valid action succeeds once; invalid/conflicting action is blocked; related data is consistent; audit contains actor, timestamp and reason. | I5: Functional + RBAC + Integration | J5: Critical | L5: Not Run
A6: TC-003 | B6: SCR-003 | C6: Reservations | D6: Reservation Calendar | E6: Complete primary Reservation Calendar workflow with valid data and verify one invalid/unauthorized path. | F6: Test property, role and dependent master data exist. | G6: 1. Sign in with authorized role. 2. Open screen. 3. Search/create/edit/process primary record. 4. Validate status and related screen. 5. Verify audit. | H6: Valid action succeeds once; invalid/conflicting action is blocked; related data is consistent; audit contains actor, timestamp and reason. | I6: Functional + RBAC + Integration | J6: Critical | L6: Not Run
A7: TC-004 | B7: SCR-004 | C7: Reservations | D7: New Reservation | E7: Complete primary New Reservation workflow with valid data and verify one invalid/unauthorized path. | F7: Test property, role and dependent master data exist. | G7: 1. Sign in with authorized role. 2. Open screen. 3. Search/create/edit/process primary record. 4. Validate status and related screen. 5. Verify audit. | H7: Valid action succeeds once; invalid/conflicting action is blocked; related data is consistent; audit contains actor, timestamp and reason. | I7: Functional + RBAC + Integration | J7: Critical | L7: Not Run
A8: TC-005 | B8: SCR-005 | C8: Front Desk | D8: Guest Check-In | E8: Complete primary Guest Check-In workflow with valid data and verify one invalid/unauthorized path. | F8: Test property, role and dependent master data exist. | G8: 1. Sign in with authorized role. 2. Open screen. 3. Search/create/edit/process primary record. 4. Validate status and related screen. 5. Verify audit. | H8: Valid action succeeds once; invalid/conflicting action is blocked; related data is consistent; audit contains actor, timestamp and reason. | I8: Functional + RBAC + Integration | J8: Critical | L8: Not Run
A9: TC-006 | B9: SCR-006 | C9: Housekeeping | D9: Housekeeping Operations | E9: Complete primary Housekeeping Operations workflow with valid data and verify one invalid/unauthorized path. | F9: Test property, role and dependent master data exist. | G9: 1. Sign in with authorized role. 2. Open screen. 3. Search/create/edit/process primary record. 4. Validate status and related screen. 5. Verify audit. | H9: Valid action succeeds once; invalid/conflicting action is blocked; related data is consistent; audit contains actor, timestamp and reason. | I9: Functional + RBAC + Integration | J9: Major | L9: Not Run
A10: TC-007 | B10: SCR-007 | C10: Front Desk | D10: Guest Checkout Folio | E10: Complete primary Guest Checkout Folio workflow with valid data and verify one invalid/unauthorized path. | F10: Test property, role and dependent master data exist. | G10: 1. Sign in with authorized role. 2. Open screen. 3. Search/create/edit/process primary record. 4. Validate status and related screen. 5. Verify audit. | H10: Valid action succeeds once; invalid/conflicting action is blocked; related data is consistent; audit contains actor, timestamp and reason. | I10: Functional + RBAC + Integration | J10: Critical | L10: Not Run
A11: TC-008 | B11: SCR-008 | C11: Property & Rooms | D11: Rooms and Villas Inventory | E11: Complete primary Rooms and Villas Inventory workflow with valid data and verify one invalid/unauthorized path. | F11: Test property, role and dependent master data exist. | G11: 1. Sign in with authorized role. 2. Open screen. 3. Search/create/edit/process primary record. 4. Validate status and related screen. 5. Verify audit. | H11: Valid action succeeds once; invalid/conflicting action is blocked; related data is consistent; audit contains actor, timestamp and reason. | I11: Functional + RBAC + Integration | J11: Critical | L11: Not Run
A12: TC-009 | B12: SCR-009 | C12: Guest CRM | D12: Guest Profile | E12: Complete primary Guest Profile workflow with valid data and verify one invalid/unauthorized path. | F12: Test property, role and dependent master data exist. | G12: 1. Sign in with authorized role. 2. Open screen. 3. Search/create/edit/process primary record. 4. Validate status and related screen. 5. Verify audit. | H12: Valid action succeeds once; invalid/conflicting action is blocked; related data is consistent; audit contains actor, timestamp and reason. | I12: Functional + RBAC + Integration | J12: Major | L12: Not Run
A13: TC-010 | B13: SCR-010 | C13: Guest CRM | D13: Guest Directory | E13: Complete primary Guest Directory workflow with valid data and verify one invalid/unauthorized path. | F13: Test property, role and dependent master data exist. | G13: 1. Sign in with authorized role. 2. Open screen. 3. Search/create/edit/process primary record. 4. Validate status and related screen. 5. Verify audit. | H13: Valid action succeeds once; invalid/conflicting action is blocked; related data is consistent; audit contains actor, timestamp and reason. | I13: Functional + RBAC + Integration | J13: Major | L13: Not Run
A14: TC-011 | B14: SCR-011 | C14: Property & Rooms | D14: Room Details | E14: Complete primary Room Details workflow with valid data and verify one invalid/unauthorized path. | F14: Test property, role and dependent master data exist. | G14: 1. Sign in with authorized role. 2. Open screen. 3. Search/create/edit/process primary record. 4. Validate status and related screen. 5. Verify audit. | H14: Valid action succeeds once; invalid/conflicting action is blocked; related data is consistent; audit contains actor, timestamp and reason. | I14: Functional + RBAC + Integration | J14: Critical | L14: Not Run
A15: TC-012 | B15: SCR-012 | C15: Food & Beverage | D15: Kitchen Display System | E15: Complete primary Kitchen Display System workflow with valid data and verify one invalid/unauthorized path. | F15: Test property, role and dependent master data exist. | G15: 1. Sign in with authorized role. 2. Open screen. 3. Search/create/edit/process primary record. 4. Validate status and related screen. 5. Verify audit. | H15: Valid action succeeds once; invalid/conflicting action is blocked; related data is consistent; audit contains actor, timestamp and reason. | I15: Functional + RBAC + Integration | J15: Major | L15: Not Run
... A133: TC-130 | B133: SCR-130 | C133: Partner Portal | D133: Portal Booking Management | E133: Complete primary Portal Booking Management workflow with valid data and verify one invalid/unauthorized path. | F133: Test property, role and dependent master data exist. | G133: 1. Sign in with authorized role. 2. Open screen. 3. Search/create/edit/process primary record. 4. Validate status and related screen. 5. Verify audit. | H133: Valid action succeeds once; invalid/conflicting action is blocked; related data is consistent; audit contains actor, timestamp and reason. | I133: Functional + RBAC + Integration | J133: Major | L133: Not Run

Sheet Lists & Legend
A1: Tracker Lists, Definitions & Update Guidance
A3: Development Status | B3: Progress | C3: Priority | D3: Design Status | E3: Test Status | F3: Permission Legend
A4: Not Started | B4: 0 | C4: Must Have | D4: Completed | E4: Not Run | F4: V = View
A5: UX/UI | B5: 0.1 | C5: Should Have | D5: Pending | E5: Passed | F5: C = Create
A6: Backend | B6: 0.35 | C6: Could Have | E6: Failed | F6: E = Edit
A7: Frontend | B7: 0.55 | C7: Won't Have Now | E7: Blocked | F7: D = Delete/Deactivate
A8: Integration | B8: 0.75 | F8: A = Approve/Override
A9: QA | B9: 0.9 | F9: X = No Access
A10: Blocked | B10: 0 | F10: S = Self-service only
A11: Done | B11: 1
A13: How to use | B13: 1. Update Development Status, Owner, planned dates and Remarks in Screen Requirements.
A14: Progress | B14: Progress % is calculated automatically from Development Status.
A15: Design status | B15: Screens 001-120 are completed mockups; 121-130 remain pending.
A16: Dependencies | B16: Build in Development Plan phase order; do not start dependent modules before exit criteria pass.
A17: Security | B17: All write operations require server-side permission checks and audit logging.

Sheet User Stories & Acceptance
A1: Chirala Bay Resort PMS — Priority-Based User Stories & Acceptance Criteria
A2: 390 stories sorted Must Have → Should Have → Could Have, then by dependency-based development order. Update Story Status and Assignee; Progress updates automatically.
A4: Priority Rank | B4: Development Sequence | C4: User Story ID | D4: Story Title | E4: Epic ID | F4: Module | G4: Submodule | H4: Screen ID | I4: Screen Name | J4: Story Type | K4: Persona | L4: User Story | M4: Business Value | N4: Preconditions | O4: Acceptance Criteria (Given / When / Then) | P4: Negative / Exception Criteria | Q4: Business Rules | R4: Dependencies | S4: API & Data Impact | T4: Priority | U4: Target Release | V4: Story Points | W4: Sprint | X4: Story Status | Y4: Progress % | Z4: Assignee | AA4: QA Test ID | AB4: Definition of Ready | AC4: Definition of Done | AD4: Notes
A5: 1 | B5: 1 | C5: US-026-01 | D5: View and find information in Property Settings | E5: EPIC-19 | F5: Administration | G5: Property Configuration | H5: SCR-026 | I5: Property Settings | J5: View / Search | K5: System Admin | L5: As a System Admin, I want to open Property Settings and find relevant records using search, filters and sorting, so that I can make accurate operational decisions. | M5: Provides timely visibility for property configuration and reduces manual lookup effort. | N5: Authenticated user; active property; view permission for Administration; Platform data available. | O5: Given I am authenticated as System Admin with access to the selected property, when I open Property Settings, then only permitted tenant/property data is displayed. Given matching records exist, when I search, filter or sort, then results, totals and pagination match the selected criteria. Given no records or a recoverable error, when the screen loads, then a clear empty/error state and safe retry action are shown. | P5: Cross-property data never appears; unauthorized fields are masked; invalid filters do not break the screen; unavailable services return a controlled message. | Q5: Tenant/property scope; required fields; optimistic locking; timezone-safe dates; reason mandatory for overrides; least privilege; secret masking; versioning; change approval | R5: Platform | S5: GET, POST, PUT/PATCH, DELETE /api/v1/property-settings; lookup, validation and audit endpoints; idempotency for financial/booking writes; entities: users, roles, permissions, approvals, audit_logs, templates, import_jobs | T5: Must Have | U5: MVP | V5: 3 | W5: S01-S02 | X5: Done | Y5: 1 | AA5: TC-026-A | AB5: Approved screen design; story reviewed with System Admin; dependencies, API contract, role permissions and test data identified. | AC5: Code reviewed; unit, API, UI, RBAC and integration tests pass; accessibility and responsive states verified; audit evidence captured; product owner accepts in staging. | AD5: Property Settings view: GET /iam/properties/{id}/settings, RBAC-guarded (property.view), cross-tenant denied. Live in Settings screen. Verified.
A6: 1 | B6: 2 | C6: US-026-02 | D6: Complete the primary Property Settings workflow | E6: EPIC-19 | F6: Administration | G6: Property Configuration | H6: SCR-026 | I6: Property Settings | J6: Primary Workflow | K6: System Admin | L6: As a System Admin, I want to list, search, filter, view, create, edit, cancel/delete under policy, export in Property Settings, so that the property configuration process is completed accurately without duplicate or inconsistent records. | M6: Enable administration users to manage property configuration through the Property Settings workflow with real-time status, validations and traceability. | N6: View access confirmed; required masters and linked records exist; Platform services are available; approval limit is valid. | O6: Given required fields and valid dependent records, when I submit the primary action, then mandatory, conflict, availability and status-transition rules run before save. Given validation passes, when I confirm, then the transaction is committed exactly once, a success reference is returned and related screens refresh consistently. Given the screen requirement, when tested end to end, then this outcome is met: Authorized users can complete the primary property settings workflow; invalid or conflicting actions are blocked with clear messages; saved changes appear in related screens; sensitive changes are auditable. | P6: Duplicate submission is idempotent; stale data returns a refresh/conflict message; invalid status transitions are blocked; partial failure rolls back without orphan records. | Q6: Tenant/property scope; required fields; optimistic locking; timezone-safe dates; reason mandatory for overrides; least privilege; secret masking; versioning; change approval | R6: Platform | S6: GET, POST, PUT/PATCH, DELETE /api/v1/property-settings; lookup, validation and audit endpoints; idempotency for financial/booking writes; entities: users, roles, permissions, approvals, audit_logs, templates, import_jobs | T6: Must Have | U6: MVP | V6: 5 | W6: S01-S02 | X6: Done | Y6: 1 | AA6: TC-026-B | AB6: Approved screen design; story reviewed with System Admin; dependencies, API contract, role permissions and test data identified. | AC6: Code reviewed; unit, API, UI, RBAC and integration tests pass; accessibility and responsive states verified; audit evidence captured; product owner accepts in staging. | AD6: Property Settings primary workflow: PUT with optimistic locking (stale version -> 409), validation, persists; edit form live. Verified end-to-end.
A7: 1 | B7: 3 | C7: US-026-03 | D7: Control permissions, overrides and audit for Property Settings | E7: EPIC-19 | F7: Administration | G7: Property Configuration | H7: SCR-026 | I7: Property Settings | J7: Security / Exceptions | K7: System Admin | L7: As a department supervisor or auditor, I want sensitive actions in Property Settings to follow permissions, approval limits and audit rules, so that resort operations remain secure, compliant and traceable. | M7: Reduces fraud, privacy leakage, unauthorized overrides and unresolved operational disputes. | N7: Roles, permissions, approval hierarchy and audit service are configured; allowed and denied test users exist. | O7: Given a user lacks permission, when a restricted UI action or direct API request is attempted, then access is denied without exposing protected data. Given an override, delete, reversal, merge, cancellation or approval-sensitive action, when confirmed, then reason and approval evidence are captured before processing. Given a sensitive action succeeds or fails, when audit history is reviewed, then actor, property, timestamp, before/after values, reason and correlation ID are available. | P7: Tampered IDs, expired sessions, approval-limit violations and cross-tenant requests are rejected; secrets and sensitive guest/payment fields are never written to logs. | Q7: Tenant/property scope; required fields; optimistic locking; timezone-safe dates; reason mandatory for overrides; least privilege; secret masking; versioning; change approval | R7: Platform | S7: GET, POST, PUT/PATCH, DELETE /api/v1/property-settings; lookup, validation and audit endpoints; idempotency for financial/booking writes; entities: users, roles, permissions, approvals, audit_logs, templates, import_jobs | T7: Must Have | U7: MVP | V7: 3 | W7: S01-S02 | X7: Done | Y7: 1 | AA7: TC-026-C | AB7: Approved screen design; story reviewed with System Admin; dependencies, API contract, role permissions and test data identified. | AC7: Code reviewed; unit, API, UI, RBAC and integration tests pass; accessibility and responsive states verified; audit evidence captured; product owner accepts in staging. | AD7: Security/exceptions: deny-by-default permission check (unauthorized -> 403), append-only audit_events with actor/before/after/reason/correlation. Verified: 403 for no-permission user, audit row on update.
A8: 1 | B8: 4 | C8: US-039-01 | D8: View and find information in User Management | E8: EPIC-19 | F8: Administration | G8: Identity & Access | H8: SCR-039 | I8: User Management | J8: View / Search | K8: System Admin | L8: As a System Admin, I want to open User Management and find relevant records using search, filters and sorting, so that I can make accurate operational decisions. | M8: Provides timely visibility for identity & access and reduces manual lookup effort. | N8: Authenticated user; active property; view permission for Administration; Platform data available. | O8: Given I am authenticated as System Admin with access to the selected property, when I open User Management, then only permitted tenant/property data is displayed. Given matching records exist, when I search, filter or sort, then results, totals and pagination match the selected criteria. Given no records or a recoverable error, when the screen loads, then a clear empty/error state and safe retry action are shown. | P8: Cross-property data never appears; unauthorized fields are masked; invalid filters do not break the screen; unavailable services return a controlled message. | Q8: Tenant/property scope; required fields; optimistic locking; timezone-safe dates; reason mandatory for overrides; least privilege; secret masking; versioning; change approval | R8: Platform | S8: GET, POST, PUT/PATCH, DELETE /api/v1/user-management; lookup, validation and audit endpoints; idempotency for financial/booking writes; entities: users, roles, permissions, approvals, audit_logs, templates, import_jobs | T8: Must Have | U8: MVP | V8: 3 | W8: S01-S02 | X8: Done | Y8: 1 | AA8: TC-039-A | AB8: Approved screen design; story reviewed with System Admin; dependencies, API contract, role permissions and test data identified. | AC8: Code reviewed; unit, API, UI, RBAC and integration tests pass; accessibility and responsive states verified; audit evidence captured; product owner accepts in staging. | AD8: User Management view/search matches mockup 039, fully live: rich columns (Employee ID, Department, Properties, Roles chips, Status, Last Login, MFA, Active Sessions) from real IAM joins; server-side filters Role/Property/Department/Status + search; KPI cards from /users/stats. Verified all filters return correct rows.
A9: 1 | B9: 5 | C9: US-039-02 | D9: Complete the primary User Management workflow | E9: EPIC-19 | F9: Administration | G9: Identity & Access | H9: SCR-039 | I9: User Management | J9: Primary Workflow | K9: System Admin | L9: As a System Admin, I want to list, view, create, edit, activate/deactivate, delete where safe in User Management, so that the identity & access process is completed accurately without duplicate or inconsistent records. | M9: Enable administration users to manage identity & access through the User Management workflow with real-time status, validations and traceability. | N9: View access confirmed; required masters and linked records exist; Platform services are available; approval limit is valid. | O9: Given required fields and valid dependent records, when I submit the primary action, then mandatory, conflict, availability and status-transition rules run before save. Given validation passes, when I confirm, then the transaction is committed exactly once, a success reference is returned and related screens refresh consistently. Given the screen requirement, when tested end to end, then this outcome is met: Authorized users can complete the primary user management workflow; invalid or conflicting actions are blocked with clear messages; saved changes appear in related screens; sensitive changes are auditable. | P9: Duplicate submission is idempotent; stale data returns a refresh/conflict message; invalid status transitions are blocked; partial failure rolls back without orphan records. | Q9: Tenant/property scope; required fields; optimistic locking; timezone-safe dates; reason mandatory for overrides; least privilege; secret masking; versioning; change approval | R9: Platform | S9: GET, POST, PUT/PATCH, DELETE /api/v1/user-management; lookup, validation and audit endpoints; idempotency for financial/booking writes; entities: users, roles, permissions, approvals, audit_logs, templates, import_jobs | T9: Must Have | U9: MVP | V9: 5 | W9: S01-S02 | X9: Done | Y9: 1 | AA9: TC-039-B | AB9: Approved screen design; story reviewed with System Admin; dependencies, API contract, role permissions and test data identified. | AC9: Code reviewed; unit, API, UI, RBAC and integration tests pass; accessibility and responsive states verified; audit evidence captured; product owner accepts in staging. | AD9: Primary workflow fully live: invite/create (+membership+employee), edit, activate/suspend, revoke-sessions; RBAC + audit; UI actions menu wired to real endpoints. Verified: revoke dropped active_sessions 12->10, edit/suspend reflect.
A10: 1 | B10: 6 | C10: US-039-03 | D10: Control permissions, overrides and audit for User Management | E10: EPIC-19 | F10: Administration | G10: Identity & Access | H10: SCR-039 | I10: User Management | J10: Security / Exceptions | K10: System Admin | L10: As a department supervisor or auditor, I want sensitive actions in User Management to follow permissions, approval limits and audit rules, so that resort operations remain secure, compliant and traceable. | M10: Reduces fraud, privacy leakage, unauthorized overrides and unresolved operational disputes. | N10: Roles, permissions, approval hierarchy and audit service are configured; allowed and denied test users exist. | O10: Given a user lacks permission, when a restricted UI action or direct API request is attempted, then access is denied without exposing protected data. Given an override, delete, reversal, merge, cancellation or approval-sensitive action, when confirmed, then reason and approval evidence are captured before processing. Given a sensitive action succeeds or fails, when audit history is reviewed, then actor, property, timestamp, before/after values, reason and correlation ID are available. | P10: Tampered IDs, expired sessions, approval-limit violations and cross-tenant requests are rejected; secrets and sensitive guest/payment fields are never written to logs. | Q10: Tenant/property scope; required fields; optimistic locking; timezone-safe dates; reason mandatory for overrides; least privilege; secret masking; versioning; change approval | R10: Platform | S10: GET, POST, PUT/PATCH, DELETE /api/v1/user-management; lookup, validation and audit endpoints; idempotency for financial/booking writes; entities: users, roles, permissions, approvals, audit_logs, templates, import_jobs | T10: Must Have | U10: MVP | V10: 3 | W10: S01-S02 | X10: Done | Y10: 1 | AA10: TC-039-C | AB10: Approved screen design; story reviewed with System Admin; dependencies, API contract, role permissions and test data identified. | AC10: Code reviewed; unit, API, UI, RBAC and integration tests pass; accessibility and responsive states verified; audit evidence captured; product owner accepts in staging. | AD10: Security/exceptions: deny-by-default (403), cannot self-deactivate, append-only audit for all actions incl revoke_sessions; View Activity shows real audit trail. Verified 403 + audit entries.
A11: 1 | B11: 7 | C11: US-040-01 | D11: View and find information in Invite or Edit User Access | E11: EPIC-19 | F11: Administration | G11: Identity & Access | H11: SCR-040 | I11: Invite or Edit User Access | J11: View / Search | K11: System Admin | L11: As a System Admin, I want to open Invite or Edit User Access and find relevant records using search, filters and sorting, so that I can make accurate operational decisions. | M11: Provides timely visibility for identity & access and reduces manual lookup effort. | N11: Authenticated user; active property; view permission for Administration; Platform data available. | O11: Given I am authenticated as System Admin with access to the selected property, when I open Invite or Edit User Access, then only permitted tenant/property data is displayed. Given matching records exist, when I search, filter or sort, then results, totals and pagination match the selected criteria. Given no records or a recoverable error, when the screen loads, then a clear empty/error state and safe retry action are shown. | P11: Cross-property data never appears; unauthorized fields are masked; invalid filters do not break the screen; unavailable services return a controlled message. | Q11: Tenant/property scope; required fields; optimistic locking; timezone-safe dates; reason mandatory for overrides; least privilege; secret masking; versioning; change approval | R11: Platform | S11: GET, POST, PUT/PATCH, DELETE /api/v1/invite-or-edit-user-access; lookup, validation and audit endpoints; idempotency for financial/booking writes; entities: users, roles, permissions, approvals, audit_logs, templates, import_jobs | T11: Must Have | U11: MVP | V11: 3 | W11: S01-S02 | X11: Done | Y11: 1 | AA11: TC-040-A | AB11: Approved screen design; story reviewed with System Admin; dependencies, API contract, role permissions and test data identified. | AC11: Code reviewed; unit, API, UI, RBAC and integration tests pass; accessibility and responsive states verified; audit evidence captured; product owner accepts in staging. | AD11: Invite/Edit User Access screen (mockup 040) view: loads live roles+departments+property; Edit mode loads current access (GET /users/{id}/access: roles, department, settings). RBAC user.view. Verified.
A12: 1 | B12: 8 | C12: US-040-02 | D12: Complete the primary Invite or Edit User Access workflow | E12: EPIC-19 | F12: Administration | G12: Identity & Access | H12: SCR-040 | I12: Invite or Edit User Access | J12: Primary Workflow | K12: System Admin | L12: As a System Admin, I want to list, search, filter, view, create, edit, cancel/delete under policy, export in Invite or Edit User Access, so that the identity & access process is completed accurately without duplicate or inconsistent records. | M12: Enable administration users to manage identity & access through the Invite or Edit User Access workflow with real-time status, validations and traceability. | N12: View access confirmed; required masters and linked records exist; Platform services are available; approval limit is valid. | O12: Given required fields and valid dependent records, when I submit the primary action, then mandatory, conflict, availability and status-transition rules run before save. Given validation passes, when I confirm, then the transaction is committed exactly once, a success reference is returned and related screens refresh consistently. Given the screen requirement, when tested end to end, then this outcome is met: Authorized users can complete the primary invite or edit user access workflow; invalid or conflicting actions are blocked with clear messages; saved changes appear in related screens; sensitive changes are auditable. | P12: Duplicate submission is idempotent; stale data returns a refresh/conflict message; invalid status transitions are blocked; partial failure rolls back without orphan records. | Q12: Tenant/property scope; required fields; optimistic locking; timezone-safe dates; reason mandatory for overrides; least privilege; secret masking; versioning; change approval | R12: Platform | S12: GET, POST, PUT/PATCH, DELETE /api/v1/invite-or-edit-user-access; lookup, validation and audit endpoints; idempotency for financial/booking writes; entities: users, roles, permissions, approvals, audit_logs, templates, import_jobs | T12: Must Have | U12: MVP | V12: 5 | W12: S01-S02 | X12: Done | Y12: 1 | AA12: TC-040-B | AB12: Approved screen design; story reviewed with System Admin; dependencies, API contract, role permissions and test data identified. | AC12: Code reviewed; unit, API, UI, RBAC and integration tests pass; accessibility and responsive states verified; audit evidence captured; product owner accepts in staging. | AD12: Dual-purpose primary workflow: INVITE (POST /invitations creates invited user+membership+employee+roles+settings) and EDIT (PUT /users/{id}/access updates name/department/employee, replaces role assignment set, MFA + settings, optimistic-locked). Verified: invite Deepa Iyer; edit changed roles 2->1 + MFA off, reflected in Users list.
A13: 1 | B13: 9 | C13: US-040-03 | D13: Control permissions, overrides and audit for Invite or Edit User Access | E13: EPIC-19 | F13: Administration | G13: Identity & Access | H13: SCR-040 | I13: Invite or Edit User Access | J13: Security / Exceptions | K13: System Admin | L13: As a department supervisor or auditor, I want sensitive actions in Invite or Edit User Access to follow permissions, approval limits and audit rules, so that resort operations remain secure, compliant and traceable. | M13: Reduces fraud, privacy leakage, unauthorized overrides and unresolved operational disputes. | N13: Roles, permissions, approval hierarchy and audit service are configured; allowed and denied test users exist. | O13: Given a user lacks permission, when a restricted UI action or direct API request is attempted, then access is denied without exposing protected data. Given an override, delete, reversal, merge, cancellation or approval-sensitive action, when confirmed, then reason and approval evidence are captured before processing. Given a sensitive action succeeds or fails, when audit history is reviewed, then actor, property, timestamp, before/after values, reason and correlation ID are available. | P13: Tampered IDs, expired sessions, approval-limit violations and cross-tenant requests are rejected; secrets and sensitive guest/payment fields are never written to logs. | Q13: Tenant/property scope; required fields; optimistic locking; timezone-safe dates; reason mandatory for overrides; least privilege; secret masking; versioning; change approval | R13: Platform | S13: GET, POST, PUT/PATCH, DELETE /api/v1/invite-or-edit-user-access; lookup, validation and audit endpoints; idempotency for financial/booking writes; entities: users, roles, permissions, approvals, audit_logs, templates, import_jobs | T13: Must Have | U13: MVP | V13: 3 | W13: S01-S02 | X13: Done | Y13: 1 | AA13: TC-040-C | AB13: Approved screen design; story reviewed with System Admin; dependencies, API contract, role permissions and test data identified. | AC13: Code reviewed; unit, API, UI, RBAC and integration tests pass; accessibility and responsive states verified; audit evidence captured; product owner accepts in staging. | AD13: Security/exceptions: RBAC user.create (invite) + user.update (edit) deny-by-default -> 403; optimistic version conflict -> 409; append-only audit invitation.create + user.access.update with before/after; cross-tenant rejected. Verified 403 + audit rows.
A14: 1 | B14: 10 | C14: US-041-01 | D14: View and find information in Roles and Permission Matrix | E14: EPIC-19 | F14: Administration | G14: Authorization | H14: SCR-041 | I14: Roles and Permission Matrix | J14: View / Search | K14: System Admin | L14: As a System Admin, I want to open Roles and Permission Matrix and find relevant records using search, filters and sorting, so that I can make accurate operational decisions. | M14: Provides timely visibility for authorization and reduces manual lookup effort. | N14: Authenticated user; active property; view permission for Administration; Platform data available. | O14: Given I am authenticated as System Admin with access to the selected property, when I open Roles and Permission Matrix, then only permitted tenant/property data is displayed. Given matching records exist, when I search, filter or sort, then results, totals and pagination match the selected criteria. Given no records or a recoverable error, when the screen loads, then a clear empty/error state and safe retry action are shown. | P14: Cross-property data never appears; unauthorized fields are masked; invalid filters do not break the screen; unavailable services return a controlled message. | Q14: Tenant/property scope; required fields; optimistic locking; timezone-safe dates; reason mandatory for overrides; least privilege; secret masking; versioning; change approval | R14: Platform | S14: GET, POST, PUT/PATCH, DELETE /api/v1/roles-and-permission-matrix; lookup, validation and audit endpoints; idempotency for financial/booking writes; entities: users, roles, permissions, approvals, audit_logs, templates, import_jobs | T14: Must Have | U14: MVP | V14: 3 | W14: S01-S02 | X14: Done | Y14: 1 | AA14: TC-041-A | AB14: Approved screen design; story reviewed with System Admin; dependencies, API contract, role permissions and test data identified. | AC14: Code reviewed; unit, API, UI, RBAC and integration tests pass; accessibility and responsive states verified; audit evidence captured; product owner accepts in staging. | AD14: Roles & Permission Matrix (mockup 041) view: 3-column layout, roles list with user counts, catalogue 13 modules x 7 actions, matrix loads role's permission grid + scope/limits. RBAC role.view. Verified.
A15: 1 | B15: 11 | C15: US-041-02 | D15: Complete the primary Roles and Permission Matrix workflow | E15: EPIC-19 | F15: Administration | G15: Authorization | H15: SCR-041 | I15: Roles and Permission Matrix | J15: Primary Workflow | K15: System Admin | L15: As a System Admin, I want to list, search, filter, view, create, edit, cancel/delete under policy, export in Roles and Permission Matrix, so that the authorization process is completed accurately without duplicate or inconsistent records. | M15: Enable administration users to manage authorization through the Roles and Permission Matrix workflow with real-time status, validations and traceability. | N15: View access confirmed; required masters and linked records exist; Platform services are available; approval limit is valid. | O15: Given required fields and valid dependent records, when I submit the primary action, then mandatory, conflict, availability and status-transition rules run before save. Given validation passes, when I confirm, then the transaction is committed exactly once, a success reference is returned and related screens refresh consistently. Given the screen requirement, when tested end to end, then this outcome is met: Authorized users can complete the primary roles and permission matrix workflow; invalid or conflicting actions are blocked with clear messages; saved changes appear in related screens; sensitive changes are auditable. | P15: Duplicate submission is idempotent; stale data returns a refresh/conflict message; invalid status transitions are blocked; partial failure rolls back without orphan records. | Q15: Tenant/property scope; required fields; optimistic locking; timezone-safe dates; reason mandatory for overrides; least privilege; secret masking; versioning; change approval | R15: Platform | S15: GET, POST, PUT/PATCH, DELETE /api/v1/roles-and-permission-matrix; lookup, validation and audit endpoints; idempotency for financial/booking writes; entities: users, roles, permissions, approvals, audit_logs, templates, import_jobs | T15: Must Have | U15: MVP | V15: 5 | W15: S01-S02 | X15: Done | Y15: 1 | AA15: TC-041-B | AB15: Approved screen design; story reviewed with System Admin; dependencies, API contract, role permissions and test data identified. | AC15: Code reviewed; unit, API, UI, RBAC and integration tests pass; accessibility and responsive states verified; audit evidence captured; product owner accepts in staging. | AD15: Primary workflow: toggle module.action permissions, set property/record scope + max discount/refund, Save (PUT replaces role_permissions + updates scope/limits), Add Role, Clone Role (copies perms). Verified save round-trips + reload reflects + add/clone.
A16: 1 | B16: 12 | C16: US-041-03 | D16: Control permissions, overrides and audit for Roles and Permission Matrix | E16: EPIC-19 | F16: Administration | G16: Authorization | H16: SCR-041 | I16: Roles and Permission Matrix | J16: Security / Exceptions | K16: System Admin | L16: As a department supervisor or auditor, I want sensitive actions in Roles and Permission Matrix to follow permissions, approval limits and audit rules, so that resort operations remain secure, compliant and traceable. | M16: Reduces fraud, privacy leakage, unauthorized overrides and unresolved operational disputes. | N16: Roles, permissions, approval hierarchy and audit service are configured; allowed and denied test users exist. | O16: Given a user lacks permission, when a restricted UI action or direct API request is attempted, then access is denied without exposing protected data. Given an override, delete, reversal, merge, cancellation or approval-sensitive action, when confirmed, then reason and approval evidence are captured before processing. Given a sensitive action succeeds or fails, when audit history is reviewed, then actor, property, timestamp, before/after values, reason and correlation ID are available. | P16: Tampered IDs, expired sessions, approval-limit violations and cross-tenant requests are rejected; secrets and sensitive guest/payment fields are never written to logs. | Q16: Tenant/property scope; required fields; optimistic locking; timezone-safe dates; reason mandatory for overrides; least privilege; secret masking; versioning; change approval | R16: Platform | S16: GET, POST, PUT/PATCH, DELETE /api/v1/roles-and-permission-matrix; lookup, validation and audit endpoints; idempotency for financial/booking writes; entities: users, roles, permissions, approvals, audit_logs, templates, import_jobs | T16: Must Have | U16: MVP | V16: 3 | W16: S01-S02 | X16: Done | Y16: 1 | AA16: TC-041-C | AB16: Approved screen design; story reviewed with System Admin; dependencies, API contract, role permissions and test data identified. | AC16: Code reviewed; unit, API, UI, RBAC and integration tests pass; accessibility and responsive states verified; audit evidence captured; product owner accepts in staging. | AD16: Security/exceptions: RBAC role.view/role.manage deny-by-default (unauthorized -> 403); append-only audit role.matrix.update/role.create/role.clone with before/after granted counts. Verified 403 + audit entries. Makes role permissions real for User Mgmt chips + Invite access preview.
... A37: 1 | B37: 33 | C37: US-063-03 | D37: Control permissions, overrides and audit for Room Block and Out of Order | E37: EPIC-05 | F37: Property & Rooms | G37: Availability Control | H37: SCR-063 | I37: Room Block and Out of Order | J37: Security / Exceptions | K37: Property Admin | L37: As a department supervisor or auditor, I want sensitive actions in Room Block and Out of Order to follow permissions, approval limits and audit rules, so that resort operations remain secure, compliant and traceable. | M37: Reduces fraud, privacy leakage, unauthorized overrides and unresolved operational disputes. | N37: Roles, permissions, approval hierarchy and audit service are configured; allowed and denied test users exist. | O37: Given a user lacks permission, when a restricted UI action or direct API request is attempted, then access is denied without exposing protected data. Given an override, delete, reversal, merge, cancellation or approval-sensitive action, when confirmed, then reason and approval evidence are captured before processing. Given a sensitive action succeeds or fails, when audit history is reviewed, then actor, property, timestamp, before/after values, reason and correlation ID are available. | P37: Tampered IDs, expired sessions, approval-limit violations and cross-tenant requests are rejected; secrets and sensitive guest/payment fields are never written to logs. | Q37: Tenant/property scope; required fields; optimistic locking; timezone-safe dates; reason mandatory for overrides; valid status transition; linked-record integrity | R37: Administration | S37: GET, POST, PUT/PATCH, DELETE /api/v1/room-block-and-out-of-order; lookup, validation and audit endpoints; idempotency for financial/booking writes; entities: properties, buildings, floors, room_types, rooms, amenities | T37: Must Have | U37: MVP | V37: 3 | W37: S01-S02 | X37: Done | Y37: 1 | AA37: TC-063-C | AB37: Approved screen design; story reviewed with Property Admin; dependencies, API contract, role permissions and test data identified. | AC37: Code reviewed; unit, API, UI, RBAC and integration tests pass; accessibility and responsive states verified; audit evidence captured; product owner accepts in staging. | AD37: KEY INVARIANT: a block cannot overlap a reservation or another block on the same room. This is NOT reimplemented - creating a block inserts a booking.room_calendar_entries row of kind 'maintenance', so the existing GiST exclusion constraint (schema 4) is the arbiter for both reservations and blocks. Multi-room requests are partially successful by design: free rooms block, clashing rooms return per-room conflicts. VERIFIED: (a) block over an existing block -> refused per room; (b) block over a live assigned reservation -> refused; (c) non-overlapping dates on the same room -> allowed; (d) End Early releases the calendar so the freed dates become blockable again. Security: RBAC rooms.view/rooms.edit deny-by-default (401/403), cross-tenant -> 403, end date before start -> 422, invalid block_type/severity/category -> 422, stale version -> 409. Append-only audit room_block.create/end/cancel/update.
A38: 1 | B38: 34 | C38: US-064-01 | D38: View and find information in Room Status History | E38: EPIC-05 | F38: Property & Rooms | G38: Status Audit | H38: SCR-064 | I38: Room Status History | J38: View / Search | K38: Property Admin | L38: As a Property Admin, I want to open Room Status History and find relevant records using search, filters and sorting, so that I can make accurate operational decisions. | M38: Provides timely visibility for status audit and reduces manual lookup effort. | N38: Authenticated user; active property; view permission for Property & Rooms; Administration data available. | O38: Given I am authenticated as Property Admin with access to the selected property, when I open Room Status History, then only permitted tenant/property data is displayed. Given matching records exist, when I search, filter or sort, then results, totals and pagination match the selected criteria. Given no records or a recoverable error, when the screen loads, then a clear empty/error state and safe retry action are shown. | P38: Cross-property data never appears; unauthorized fields are masked; invalid filters do not break the screen; unavailable services return a controlled message. | Q38: Tenant/property scope; required fields; optimistic locking; timezone-safe dates; reason mandatory for overrides; valid status transition; linked-record integrity | R38: Administration | S38: GET, POST/PATCH /api/v1/room-status-history; lookup, validation and audit endpoints; idempotency for financial/booking writes; entities: properties, buildings, floors, room_types, rooms, amenities | T38: Must Have | U38: MVP | V38: 3 | W38: S01-S02 | X38: Done | Y38: =IF(X38="Done",1,IF(X38="QA",0.9,IF(X38="Code Review",0.75,IF(X38="In Development",0.5,IF(X38="Ready",0.1,0))))) | AA38: TC-064-A | AB38: Approved screen design; story reviewed with Property Admin; dependencies, API contract, role permissions and test data identified. | AC38: Code reviewed; unit, API, UI, RBAC and integration tests pass; accessibility and responsive states verified; audit evidence captured; product owner accepts in staging. | AD38: Room Status History (mockup 064) at /rooms/:roomId/history, reached from the History action on a room card and the Status History button on the Room editor (059). GET /rooms/{id}/status-history returns the timeline newest first with Changed By name + role (resolved through memberships -> role_assignments -> roles) and a human Source label. Filters verified live against room 106: From/To (end date inclusive of the whole day), Status, Source and User, plus Clear/Apply. Record count badge and CSV Export follow the filtered set. GET /rooms/{id}/status-summary drives the right rail: thumbnail card, Current Status with Since + elapsed duration, Current Guest, Reservation, Linked Records and Audit Information. RBAC rooms.view.
A39: 1 | B39: 35 | C39: US-064-02 | D39: Complete the primary Room Status History workflow | E39: EPIC-05 | F39: Property & Rooms | G39: Status Audit | H39: SCR-064 | I39: Room Status History | J39: Primary Workflow | K39: Property Admin | L39: As a Property Admin, I want to view, filter, search, drill down, export, refresh in Room Status History, so that the status audit process is completed accurately without duplicate or inconsistent records. | M39: Enable property & rooms users to manage status audit through the Room Status History workflow with real-time status, validations and traceability. | N39: View access confirmed; required masters and linked records exist; Administration services are available; approval limit is valid. | O39: Given required fields and valid dependent records, when I submit the primary action, then mandatory, conflict, availability and status-transition rules run before save. Given validation passes, when I confirm, then the transaction is committed exactly once, a success reference is returned and related screens refresh consistently. Given the screen requirement, when tested end to end, then this outcome is met: Authorized users can complete the primary room status history workflow; invalid or conflicting actions are blocked with clear messages; saved changes appear in related screens; sensitive changes are auditable. | P39: Duplicate submission is idempotent; stale data returns a refresh/conflict message; invalid status transitions are blocked; partial failure rolls back without orphan records. | Q39: Tenant/property scope; required fields; optimistic locking; timezone-safe dates; reason mandatory for overrides; valid status transition; linked-record integrity | R39: Administration | S39: GET, POST/PATCH /api/v1/room-status-history; lookup, validation and audit endpoints; idempotency for financial/booking writes; entities: properties, buildings, floors, room_types, rooms, amenities | T39: Must Have | U39: MVP | V39: 5 | W39: S01-S02 | X39: Done | Y39: =IF(X39="Done",1,IF(X39="QA",0.9,IF(X39="Code Review",0.75,IF(X39="In Development",0.5,IF(X39="Ready",0.1,0))))) | AA39: TC-064-B | AB39: Approved screen design; story reviewed with Property Admin; dependencies, API contract, role permissions and test data identified. | AC39: Code reviewed; unit, API, UI, RBAC and integration tests pass; accessibility and responsive states verified; audit evidence captured; product owner accepts in staging. | AD39: New table operations.room_status_events (migration 0009) is the append-only log; there is no update or delete endpoint, because on this screen a correction is a new event, not an edit. Events are written by the paths that actually change a room's state, in the same transaction as the change: block create/end/cancel (blocks_routes), room create and any status / service_status change (rooms_routes), and check-in / check-out (flow.py, carrying the reservation number as the source reference). Existing history was backfilled from booking.room_blocks and operations.room_condition and is marked source='system' so it is honestly distinguishable from live capture. 'Since' walks back the run of consecutive events sharing the current status, so it reads as the start of the current spell. VERIFIED live: a correction through the dialog appended a Clean / Housekeeping / Kishore Admin row; creating an Out of Order block appended 'Out of Order / Room Block' with reference MM260921-017; ending it appended 'Available / Room Block'.
A40: 1 | B40: 36 | C40: US-064-03 | D40: Control permissions, overrides and audit for Room Status History | E40: EPIC-05 | F40: Property & Rooms | G40: Status Audit | H40: SCR-064 | I40: Room Status History | J40: Security / Exceptions | K40: Property Admin | L40: As a department supervisor or auditor, I want sensitive actions in Room Status History to follow permissions, approval limits and audit rules, so that resort operations remain secure, compliant and traceable. | M40: Reduces fraud, privacy leakage, unauthorized overrides and unresolved operational disputes. | N40: Roles, permissions, approval hierarchy and audit service are configured; allowed and denied test users exist. | O40: Given a user lacks permission, when a restricted UI action or direct API request is attempted, then access is denied without exposing protected data. Given an override, delete, reversal, merge, cancellation or approval-sensitive action, when confirmed, then reason and approval evidence are captured before processing. Given a sensitive action succeeds or fails, when audit history is reviewed, then actor, property, timestamp, before/after values, reason and correlation ID are available. | P40: Tampered IDs, expired sessions, approval-limit violations and cross-tenant requests are rejected; secrets and sensitive guest/payment fields are never written to logs. | Q40: Tenant/property scope; required fields; optimistic locking; timezone-safe dates; reason mandatory for overrides; valid status transition; linked-record integrity | R40: Administration | S40: GET, POST/PATCH /api/v1/room-status-history; lookup, validation and audit endpoints; idempotency for financial/booking writes; entities: properties, buildings, floors, room_types, rooms, amenities | T40: Must Have | U40: MVP | V40: 3 | W40: S01-S02 | X40: Done | Y40: =IF(X40="Done",1,IF(X40="QA",0.9,IF(X40="Code Review",0.75,IF(X40="In Development",0.5,IF(X40="Ready",0.1,0))))) | AA40: TC-064-C | AB40: Approved screen design; story reviewed with Property Admin; dependencies, API contract, role permissions and test data identified. | AC40: Code reviewed; unit, API, UI, RBAC and integration tests pass; accessibility and responsive states verified; audit evidence captured; product owner accepts in staging. | AD40: The screen is read-only by design and says so: the amber panel explains that a correction is appended rather than replacing what was recorded. The one write is POST /rooms/{id}/housekeeping-status (RBAC rooms.edit), which moves the room's current housekeeping state and records the resulting event attributed to the caller; the dialog offers only clean/dirty/cleaning/inspected and directs occupancy and out-of-order corrections to the reservation and the block, so the room calendar can never drift. Reads require rooms.view; both endpoints call assert_property_in_org, so a cross-tenant room is 403 and an unknown room is 404. Invalid housekeeping status -> 422. Current status mirrors the Rooms grid precedence (block > in-house > inactive > service status > cleanliness) so the two screens can never disagree.
A41: 1 | B41: 37 | C41: US-123-01 | D41: View and find information in Property Master Setup | E41: EPIC-19 | F41: Administration | G41: Property Master | H41: SCR-123 | I41: Property Master Setup | J41: View / Search | K41: System Admin | L41: As a System Admin, I want to open Property Master Setup and find relevant records using search, filters and sorting, so that I can make accurate operational decisions. | M41: Provides timely visibility for property master and reduces manual lookup effort. | N41: Authenticated user; active property; view permission for Administration; Platform data available. | O41: Given I am authenticated as System Admin with access to the selected property, when I open Property Master Setup, then only permitted tenant/property data is displayed. Given matching records exist, when I search, filter or sort, then results, totals and pagination match the selected criteria. Given no records or a recoverable error, when the screen loads, then a clear empty/error state and safe retry action are shown. | P41: Cross-property data never appears; unauthorized fields are masked; invalid filters do not break the screen; unavailable services return a controlled message. | Q41: Tenant/property scope; required fields; optimistic locking; timezone-safe dates; reason mandatory for overrides; least privilege; secret masking; versioning; change approval | R41: Platform | S41: GET, POST, PUT/PATCH, DELETE /api/v1/property-master-setup; lookup, validation and audit endpoints; idempotency for financial/booking writes; entities: users, roles, permissions, approvals, audit_logs, templates, import_jobs | T41: Must Have | U41: MVP | V41: 3 | W41: S01-S02 | X41: Backlog | Y41: =IF(X41="Done",1,IF(X41="QA",0.9,IF(X41="Code Review",0.75,IF(X41="In Development",0.5,IF(X41="Ready",0.1,0))))) | AA41: TC-123-A | AB41: Approved screen design; story reviewed with System Admin; dependencies, API contract, role permissions and test data identified. | AC41: Code reviewed; unit, API, UI, RBAC and integration tests pass; accessibility and responsive states verified; audit evidence captured; product owner accepts in staging.
A42: 1 | B42: 38 | C42: US-123-02 | D42: Complete the primary Property Master Setup workflow | E42: EPIC-19 | F42: Administration | G42: Property Master | H42: SCR-123 | I42: Property Master Setup | J42: Primary Workflow | K42: System Admin | L42: As a System Admin, I want to list, view, create, edit, activate/deactivate, delete where safe in Property Master Setup, so that the property master process is completed accurately without duplicate or inconsistent records. | M42: Enable administration users to manage property master through the Property Master Setup workflow with real-time status, validations and traceability. | N42: View access confirmed; required masters and linked records exist; Platform services are available; approval limit is valid. | O42: Given required fields and valid dependent records, when I submit the primary action, then mandatory, conflict, availability and status-transition rules run before save. Given validation passes, when I confirm, then the transaction is committed exactly once, a success reference is returned and related screens refresh consistently. Given the screen requirement, when tested end to end, then this outcome is met: Authorized users can complete the primary property master setup workflow; invalid or conflicting actions are blocked with clear messages; saved changes appear in related screens; sensitive changes are auditable. | P42: Duplicate submission is idempotent; stale data returns a refresh/conflict message; invalid status transitions are blocked; partial failure rolls back without orphan records. | Q42: Tenant/property scope; required fields; optimistic locking; timezone-safe dates; reason mandatory for overrides; least privilege; secret masking; versioning; change approval | R42: Platform | S42: GET, POST, PUT/PATCH, DELETE /api/v1/property-master-setup; lookup, validation and audit endpoints; idempotency for financial/booking writes; entities: users, roles, permissions, approvals, audit_logs, templates, import_jobs | T42: Must Have | U42: MVP | V42: 5 | W42: S01-S02 | X42: Backlog | Y42: =IF(X42="Done",1,IF(X42="QA",0.9,IF(X42="Code Review",0.75,IF(X42="In Development",0.5,IF(X42="Ready",0.1,0))))) | AA42: TC-123-B | AB42: Approved screen design; story reviewed with System Admin; dependencies, API contract, role permissions and test data identified. | AC42: Code reviewed; unit, API, UI, RBAC and integration tests pass; accessibility and responsive states verified; audit evidence captured; product owner accepts in staging.
A43: 1 | B43: 39 | C43: US-123-03 | D43: Control permissions, overrides and audit for Property Master Setup | E43: EPIC-19 | F43: Administration | G43: Property Master | H43: SCR-123 | I43: Property Master Setup | J43: Security / Exceptions | K43: System Admin | L43: As a department supervisor or auditor, I want sensitive actions in Property Master Setup to follow permissions, approval limits and audit rules, so that resort operations remain secure, compliant and traceable. | M43: Reduces fraud, privacy leakage, unauthorized overrides and unresolved operational disputes. | N43: Roles, permissions, approval hierarchy and audit service are configured; allowed and denied test users exist. | O43: Given a user lacks permission, when a restricted UI action or direct API request is attempted, then access is denied without exposing protected data. Given an override, delete, reversal, merge, cancellation or approval-sensitive action, when confirmed, then reason and approval evidence are captured before processing. Given a sensitive action succeeds or fails, when audit history is reviewed, then actor, property, timestamp, before/after values, reason and correlation ID are available. | P43: Tampered IDs, expired sessions, approval-limit violations and cross-tenant requests are rejected; secrets and sensitive guest/payment fields are never written to logs. | Q43: Tenant/property scope; required fields; optimistic locking; timezone-safe dates; reason mandatory for overrides; least privilege; secret masking; versioning; change approval | R43: Platform | S43: GET, POST, PUT/PATCH, DELETE /api/v1/property-master-setup; lookup, validation and audit endpoints; idempotency for financial/booking writes; entities: users, roles, permissions, approvals, audit_logs, templates, import_jobs | T43: Must Have | U43: MVP | V43: 3 | W43: S01-S02 | X43: Backlog | Y43: =IF(X43="Done",1,IF(X43="QA",0.9,IF(X43="Code Review",0.75,IF(X43="In Development",0.5,IF(X43="Ready",0.1,0))))) | AA43: TC-123-C | AB43: Approved screen design; story reviewed with System Admin; dependencies, API contract, role permissions and test data identified. | AC43: Code reviewed; unit, API, UI, RBAC and integration tests pass; accessibility and responsive states verified; audit evidence captured; product owner accepts in staging.
A44: 1 | B44: 40 | C44: US-125-01 | D44: View and find information in Notification Template Management | E44: EPIC-19 | F44: Administration | G44: Notification Setup | H44: SCR-125 | I44: Notification Template Management | J44: View / Search | K44: System Admin | L44: As a System Admin, I want to open Notification Template Management and find relevant records using search, filters and sorting, so that I can make accurate operational decisions. | M44: Provides timely visibility for notification setup and reduces manual lookup effort. | N44: Authenticated user; active property; view permission for Administration; Platform data available. | O44: Given I am authenticated as System Admin with access to the selected property, when I open Notification Template Management, then only permitted tenant/property data is displayed. Given matching records exist, when I search, filter or sort, then results, totals and pagination match the selected criteria. Given no records or a recoverable error, when the screen loads, then a clear empty/error state and safe retry action are shown. | P44: Cross-property data never appears; unauthorized fields are masked; invalid filters do not break the screen; unavailable services return a controlled message. | Q44: Tenant/property scope; required fields; optimistic locking; timezone-safe dates; reason mandatory for overrides; least privilege; secret masking; versioning; change approval | R44: Platform | S44: GET, POST, PUT/PATCH, DELETE /api/v1/notification-template-management; lookup, validation and audit endpoints; idempotency for financial/booking writes; entities: users, roles, permissions, approvals, audit_logs, templates, import_jobs | T44: Must Have | U44: MVP | V44: 3 | W44: S01-S02 | X44: Backlog | Y44: =IF(X44="Done",1,IF(X44="QA",0.9,IF(X44="Code Review",0.75,IF(X44="In Development",0.5,IF(X44="Ready",0.1,0))))) | AA44: TC-125-A | AB44: Approved screen design; story reviewed with System Admin; dependencies, API contract, role permissions and test data identified. | AC44: Code reviewed; unit, API, UI, RBAC and integration tests pass; accessibility and responsive states verified; audit evidence captured; product owner accepts in staging.
A45: 1 | B45: 41 | C45: US-125-02 | D45: Complete the primary Notification Template Management workflow | E45: EPIC-19 | F45: Administration | G45: Notification Setup | H45: SCR-125 | I45: Notification Template Management | J45: Primary Workflow | K45: System Admin | L45: As a System Admin, I want to list, view, create, edit, activate/deactivate, delete where safe in Notification Template Management, so that the notification setup process is completed accurately without duplicate or inconsistent records. | M45: Enable administration users to manage notification setup through the Notification Template Management workflow with real-time status, validations and traceability. | N45: View access confirmed; required masters and linked records exist; Platform services are available; approval limit is valid. | O45: Given required fields and valid dependent records, when I submit the primary action, then mandatory, conflict, availability and status-transition rules run before save. Given validation passes, when I confirm, then the transaction is committed exactly once, a success reference is returned and related screens refresh consistently. Given the screen requirement, when tested end to end, then this outcome is met: Authorized users can complete the primary notification template management workflow; invalid or conflicting actions are blocked with clear messages; saved changes appear in related screens; sensitive changes are auditable. | P45: Duplicate submission is idempotent; stale data returns a refresh/conflict message; invalid status transitions are blocked; partial failure rolls back without orphan records. | Q45: Tenant/property scope; required fields; optimistic locking; timezone-safe dates; reason mandatory for overrides; least privilege; secret masking; versioning; change approval | R45: Platform | S45: GET, POST, PUT/PATCH, DELETE /api/v1/notification-template-management; lookup, validation and audit endpoints; idempotency for financial/booking writes; entities: users, roles, permissions, approvals, audit_logs, templates, import_jobs | T45: Must Have | U45: MVP | V45: 5 | W45: S01-S02 | X45: Backlog | Y45: =IF(X45="Done",1,IF(X45="QA",0.9,IF(X45="Code Review",0.75,IF(X45="In Development",0.5,IF(X45="Ready",0.1,0))))) | AA45: TC-125-B | AB45: Approved screen design; story reviewed with System Admin; dependencies, API contract, role permissions and test data identified. | AC45: Code reviewed; unit, API, UI, RBAC and integration tests pass; accessibility and responsive states verified; audit evidence captured; product owner accepts in staging.
A46: 1 | B46: 42 | C46: US-125-03 | D46: Control permissions, overrides and audit for Notification Template Management | E46: EPIC-19 | F46: Administration | G46: Notification Setup | H46: SCR-125 | I46: Notification Template Management | J46: Security / Exceptions | K46: System Admin | L46: As a department supervisor or auditor, I want sensitive actions in Notification Template Management to follow permissions, approval limits and audit rules, so that resort operations remain secure, compliant and traceable. | M46: Reduces fraud, privacy leakage, unauthorized overrides and unresolved operational disputes. | N46: Roles, permissions, approval hierarchy and audit service are configured; allowed and denied test users exist. | O46: Given a user lacks permission, when a restricted UI action or direct API request is attempted, then access is denied without exposing protected data. Given an override, delete, reversal, merge, cancellation or approval-sensitive action, when confirmed, then reason and approval evidence are captured before processing. Given a sensitive action succeeds or fails, when audit history is reviewed, then actor, property, timestamp, before/after values, reason and correlation ID are available. | P46: Tampered IDs, expired sessions, approval-limit violations and cross-tenant requests are rejected; secrets and sensitive guest/payment fields are never written to logs. | Q46: Tenant/property scope; required fields; optimistic locking; timezone-safe dates; reason mandatory for overrides; least privilege; secret masking; versioning; change approval | R46: Platform | S46: GET, POST, PUT/PATCH, DELETE /api/v1/notification-template-management; lookup, validation and audit endpoints; idempotency for financial/booking writes; entities: users, roles, permissions, approvals, audit_logs, templates, import_jobs | T46: Must Have | U46: MVP | V46: 3 | W46: S01-S02 | X46: Backlog | Y46: =IF(X46="Done",1,IF(X46="QA",0.9,IF(X46="Code Review",0.75,IF(X46="In Development",0.5,IF(X46="Ready",0.1,0))))) | AA46: TC-125-C | AB46: Approved screen design; story reviewed with System Admin; dependencies, API contract, role permissions and test data identified. | AC46: Code reviewed; unit, API, UI, RBAC and integration tests pass; accessibility and responsive states verified; audit evidence captured; product owner accepts in staging.
A47: 1 | B47: 43 | C47: US-126-01 | D47: View and find information in Data Import and Export Center | E47: EPIC-19 | F47: Administration | G47: Data Operations | H47: SCR-126 | I47: Data Import and Export Center | J47: View / Search | K47: System Admin | L47: As a System Admin, I want to open Data Import and Export Center and find relevant records using search, filters and sorting, so that I can make accurate operational decisions. | M47: Provides timely visibility for data operations and reduces manual lookup effort. | N47: Authenticated user; active property; view permission for Administration; Platform data available. | O47: Given I am authenticated as System Admin with access to the selected property, when I open Data Import and Export Center, then only permitted tenant/property data is displayed. Given matching records exist, when I search, filter or sort, then results, totals and pagination match the selected criteria. Given no records or a recoverable error, when the screen loads, then a clear empty/error state and safe retry action are shown. | P47: Cross-property data never appears; unauthorized fields are masked; invalid filters do not break the screen; unavailable services return a controlled message. | Q47: Tenant/property scope; required fields; optimistic locking; timezone-safe dates; reason mandatory for overrides; least privilege; secret masking; versioning; change approval | R47: Platform | S47: GET, POST, PUT/PATCH, DELETE /api/v1/data-import-and-export-center; lookup, validation and audit endpoints; idempotency for financial/booking writes; entities: users, roles, permissions, approvals, audit_logs, templates, import_jobs | T47: Must Have | U47: MVP | V47: 3 | W47: S01-S02 | X47: Backlog | Y47: =IF(X47="Done",1,IF(X47="QA",0.9,IF(X47="Code Review",0.75,IF(X47="In Development",0.5,IF(X47="Ready",0.1,0))))) | AA47: TC-126-A | AB47: Approved screen design; story reviewed with System Admin; dependencies, API contract, role permissions and test data identified. | AC47: Code reviewed; unit, API, UI, RBAC and integration tests pass; accessibility and responsive states verified; audit evidence captured; product owner accepts in staging.
A48: 1 | B48: 44 | C48: US-126-02 | D48: Complete the primary Data Import and Export Center workflow | E48: EPIC-19 | F48: Administration | G48: Data Operations | H48: SCR-126 | I48: Data Import and Export Center | J48: Primary Workflow | K48: System Admin | L48: As a System Admin, I want to list, search, filter, view, create, edit, cancel/delete under policy, export in Data Import and Export Center, so that the data operations process is completed accurately without duplicate or inconsistent records. | M48: Enable administration users to manage data operations through the Data Import and Export Center workflow with real-time status, validations and traceability. | N48: View access confirmed; required masters and linked records exist; Platform services are available; approval limit is valid. | O48: Given required fields and valid dependent records, when I submit the primary action, then mandatory, conflict, availability and status-transition rules run before save. Given validation passes, when I confirm, then the transaction is committed exactly once, a success reference is returned and related screens refresh consistently. Given the screen requirement, when tested end to end, then this outcome is met: Authorized users can complete the primary data import and export center workflow; invalid or conflicting actions are blocked with clear messages; saved changes appear in related screens; sensitive changes are auditable. | P48: Duplicate submission is idempotent; stale data returns a refresh/conflict message; invalid status transitions are blocked; partial failure rolls back without orphan records. | Q48: Tenant/property scope; required fields; optimistic locking; timezone-safe dates; reason mandatory for overrides; least privilege; secret masking; versioning; change approval | R48: Platform | S48: GET, POST, PUT/PATCH, DELETE /api/v1/data-import-and-export-center; lookup, validation and audit endpoints; idempotency for financial/booking writes; entities: users, roles, permissions, approvals, audit_logs, templates, import_jobs | T48: Must Have | U48: MVP | V48: 5 | W48: S01-S02 | X48: Backlog | Y48: =IF(X48="Done",1,IF(X48="QA",0.9,IF(X48="Code Review",0.75,IF(X48="In Development",0.5,IF(X48="Ready",0.1,0))))) | AA48: TC-126-B | AB48: Approved screen design; story reviewed with System Admin; dependencies, API contract, role permissions and test data identified. | AC48: Code reviewed; unit, API, UI, RBAC and integration tests pass; accessibility and responsive states verified; audit evidence captured; product owner accepts in staging.
A49: 1 | B49: 45 | C49: US-126-03 | D49: Control permissions, overrides and audit for Data Import and Export Center | E49: EPIC-19 | F49: Administration | G49: Data Operations | H49: SCR-126 | I49: Data Import and Export Center | J49: Security / Exceptions | K49: System Admin | L49: As a department supervisor or auditor, I want sensitive actions in Data Import and Export Center to follow permissions, approval limits and audit rules, so that resort operations remain secure, compliant and traceable. | M49: Reduces fraud, privacy leakage, unauthorized overrides and unresolved operational disputes. | N49: Roles, permissions, approval hierarchy and audit service are configured; allowed and denied test users exist. | O49: Given a user lacks permission, when a restricted UI action or direct API request is attempted, then access is denied without exposing protected data. Given an override, delete, reversal, merge, cancellation or approval-sensitive action, when confirmed, then reason and approval evidence are captured before processing. Given a sensitive action succeeds or fails, when audit history is reviewed, then actor, property, timestamp, before/after values, reason and correlation ID are available. | P49: Tampered IDs, expired sessions, approval-limit violations and cross-tenant requests are rejected; secrets and sensitive guest/payment fields are never written to logs. | Q49: Tenant/property scope; required fields; optimistic locking; timezone-safe dates; reason mandatory for overrides; least privilege; secret masking; versioning; change approval | R49: Platform | S49: GET, POST, PUT/PATCH, DELETE /api/v1/data-import-and-export-center; lookup, validation and audit endpoints; idempotency for financial/booking writes; entities: users, roles, permissions, approvals, audit_logs, templates, import_jobs | T49: Must Have | U49: MVP | V49: 3 | W49: S01-S02 | X49: Backlog | Y49: =IF(X49="Done",1,IF(X49="QA",0.9,IF(X49="Code Review",0.75,IF(X49="In Development",0.5,IF(X49="Ready",0.1,0))))) | AA49: TC-126-C | AB49: Approved screen design; story reviewed with System Admin; dependencies, API contract, role permissions and test data identified. | AC49: Code reviewed; unit, API, UI, RBAC and integration tests pass; accessibility and responsive states verified; audit evidence captured; product owner accepts in staging.
A50: 1 | B50: 46 | C50: US-008-01 | D50: View and find information in Rooms and Villas Inventory | E50: EPIC-05 | F50: Property & Rooms | G50: Inventory | H50: SCR-008 | I50: Rooms and Villas Inventory | J50: View / Search | K50: Property Admin | L50: As a Property Admin, I want to open Rooms and Villas Inventory and find relevant records using search, filters and sorting, so that I can make accurate operational decisions. | M50: Provides timely visibility for inventory and reduces manual lookup effort. | N50: Authenticated user; active property; view permission for Property & Rooms; Administration data available. | O50: Given I am authenticated as Property Admin with access to the selected property, when I open Rooms and Villas Inventory, then only permitted tenant/property data is displayed. Given matching records exist, when I search, filter or sort, then results, totals and pagination match the selected criteria. Given no records or a recoverable error, when the screen loads, then a clear empty/error state and safe retry action are shown. | P50: Cross-property data never appears; unauthorized fields are masked; invalid filters do not break the screen; unavailable services return a controlled message. | Q50: Tenant/property scope; required fields; optimistic locking; timezone-safe dates; reason mandatory for overrides; valid status transition; linked-record integrity | R50: Administration | S50: GET, POST, PUT/PATCH, DELETE /api/v1/rooms-and-villas-inventory; lookup, validation and audit endpoints; idempotency for financial/booking writes; entities: properties, buildings, floors, room_types, rooms, amenities | T50: Must Have | U50: MVP | V50: 3 | W50: S03-S04 | X50: Done | Y50: 1 | AA50: TC-008-A | AB50: Approved screen design; story reviewed with Property Admin; dependencies, API contract, role permissions and test data identified. | AC50: Code reviewed; unit, API, UI, RBAC and integration tests pass; accessibility and responsive states verified; audit evidence captured; product owner accepts in staging. | AD50: Rooms & Villas Inventory (mockup 008) view/search: GET /booking/rooms property-scoped grid+list with live KPI cards (total/occupied/available/cleaning/maintenance) and server-side Floor/Room Type/Status filters over 44 real rooms. Occupancy and housekeeping state are DERIVED at query time from booking.stays/reservation_units and operations.room_condition, never stored. RBAC rooms.view. Verified: 44 rooms, state=cleaning returns 24.
A51: 1 | B51: 47 | C51: US-008-02 | D51: Complete the primary Rooms and Villas Inventory workflow | E51: EPIC-05 | F51: Property & Rooms | G51: Inventory | H51: SCR-008 | I51: Rooms and Villas Inventory | J51: Primary Workflow | K51: Property Admin | L51: As a Property Admin, I want to list, search, filter, view, create, edit, cancel/delete under policy, export in Rooms and Villas Inventory, so that the inventory process is completed accurately without duplicate or inconsistent records. | M51: Enable property & rooms users to manage inventory through the Rooms and Villas Inventory workflow with real-time status, validations and traceability. | N51: View access confirmed; required masters and linked records exist; Administration services are available; approval limit is valid. | O51: Given required fields and valid dependent records, when I submit the primary action, then mandatory, conflict, availability and status-transition rules run before save. Given validation passes, when I confirm, then the transaction is committed exactly once, a success reference is returned and related screens refresh consistently. Given the screen requirement, when tested end to end, then this outcome is met: Authorized users can complete the primary rooms and villas inventory workflow; invalid or conflicting actions are blocked with clear messages; saved changes appear in related screens; sensitive changes are auditable. | P51: Duplicate submission is idempotent; stale data returns a refresh/conflict message; invalid status transitions are blocked; partial failure rolls back without orphan records. | Q51: Tenant/property scope; required fields; optimistic locking; timezone-safe dates; reason mandatory for overrides; valid status transition; linked-record integrity | R51: Administration | S51: GET, POST, PUT/PATCH, DELETE /api/v1/rooms-and-villas-inventory; lookup, validation and audit endpoints; idempotency for financial/booking writes; entities: properties, buildings, floors, room_types, rooms, amenities | T51: Must Have | U51: MVP | V51: 5 | W51: S03-S04 | X51: Done | Y51: 1 | AA51: TC-008-B | AB51: Approved screen design; story reviewed with Property Admin; dependencies, API contract, role permissions and test data identified. | AC51: Code reviewed; unit, API, UI, RBAC and integration tests pass; accessibility and responsive states verified; audit evidence captured; product owner accepts in staging. | AD51: Inventory primary workflow: grid/list toggle, Add Room, View, Assign (real reservation assignment via the GiST-guarded flow endpoint) and Block/Unblock. The Blocks tab now hosts the full Room Block & Out of Order screen (063) rather than a placeholder list. Verified assign 200 + 409 on overlap, block round-trip. Remaining mockup gap: the 5th 'Rate Plans' tab is present but its module (screen 066) is not built.
A52: 1 | B52: 48 | C52: US-008-03 | D52: Control permissions, overrides and audit for Rooms and Villas Inventory | E52: EPIC-05 | F52: Property & Rooms | G52: Inventory | H52: SCR-008 | I52: Rooms and Villas Inventory | J52: Security / Exceptions | K52: Property Admin | L52: As a department supervisor or auditor, I want sensitive actions in Rooms and Villas Inventory to follow permissions, approval limits and audit rules, so that resort operations remain secure, compliant and traceable. | M52: Reduces fraud, privacy leakage, unauthorized overrides and unresolved operational disputes. | N52: Roles, permissions, approval hierarchy and audit service are configured; allowed and denied test users exist. | O52: Given a user lacks permission, when a restricted UI action or direct API request is attempted, then access is denied without exposing protected data. Given an override, delete, reversal, merge, cancellation or approval-sensitive action, when confirmed, then reason and approval evidence are captured before processing. Given a sensitive action succeeds or fails, when audit history is reviewed, then actor, property, timestamp, before/after values, reason and correlation ID are available. | P52: Tampered IDs, expired sessions, approval-limit violations and cross-tenant requests are rejected; secrets and sensitive guest/payment fields are never written to logs. | Q52: Tenant/property scope; required fields; optimistic locking; timezone-safe dates; reason mandatory for overrides; valid status transition; linked-record integrity | R52: Administration | S52: GET, POST, PUT/PATCH, DELETE /api/v1/rooms-and-villas-inventory; lookup, validation and audit endpoints; idempotency for financial/booking writes; entities: properties, buildings, floors, room_types, rooms, amenities | T52: Must Have | U52: MVP | V52: 3 | W52: S03-S04 | X52: Done | Y52: 1 | AA52: TC-008-C | AB52: Approved screen design; story reviewed with Property Admin; dependencies, API contract, role permissions and test data identified. | AC52: Code reviewed; unit, API, UI, RBAC and integration tests pass; accessibility and responsive states verified; audit evidence captured; product owner accepts in staging. | AD52: Security/exceptions: deny-by-default rooms.view (no token -> 401, no permission -> 403); cross-tenant property_id -> 403 via assert_property_in_org; blocking a room with an in-house stay -> 409 (guard implemented; not exercised - no in-house stays in current data); append-only audit room.block/room.unblock. Verified 401/403/403.
A53: 1 | B53: 49 | C53: US-011-01 | D53: View and find information in Room Details | E53: EPIC-05 | F53: Property & Rooms | G53: Room Details | H53: SCR-011 | I53: Room Details | J53: View / Search | K53: Property Admin | L53: As a Property Admin, I want to open Room Details and find relevant records using search, filters and sorting, so that I can make accurate operational decisions. | M53: Provides timely visibility for room details and reduces manual lookup effort. | N53: Authenticated user; active property; view permission for Property & Rooms; Administration data available. | O53: Given I am authenticated as Property Admin with access to the selected property, when I open Room Details, then only permitted tenant/property data is displayed. Given matching records exist, when I search, filter or sort, then results, totals and pagination match the selected criteria. Given no records or a recoverable error, when the screen loads, then a clear empty/error state and safe retry action are shown. | P53: Cross-property data never appears; unauthorized fields are masked; invalid filters do not break the screen; unavailable services return a controlled message. | Q53: Tenant/property scope; required fields; optimistic locking; timezone-safe dates; reason mandatory for overrides; valid status transition; linked-record integrity | R53: Administration | S53: GET, POST, PUT/PATCH, DELETE /api/v1/room-details; lookup, validation and audit endpoints; idempotency for financial/booking writes; entities: properties, buildings, floors, room_types, rooms, amenities | T53: Must Have | U53: MVP | V53: 3 | W53: S03-S04 | X53: Done | Y53: =IF(X53="Done",1,IF(X53="QA",0.9,IF(X53="Code Review",0.75,IF(X53="In Development",0.5,IF(X53="Ready",0.1,0))))) | AA53: TC-011-A | AB53: Approved screen design; story reviewed with Property Admin; dependencies, API contract, role permissions and test data identified. | AC53: Code reviewed; unit, API, UI, RBAC and integration tests pass; accessibility and responsive states verified; audit evidence captured; product owner accepts in staging. | AD53: Room Details (mockup 011) at /rooms/:roomId — now the target of the room card's View action and of screen 064's 'Room N' breadcrumb and 'Back to Room', both of which previously dropped the user straight into the edit form. GET /rooms/{id}/overview drives the header, gallery, Overview tab and right rail: breadcrumb from the linked building/floor names (falling back to the free-text fields), room type, size, capacity, view, bed type and base rate. Gallery shows the room's own photos and falls back to the room type's when it has none, with prev/next, a 1/N counter, a '+N more' badge and a lightbox. RBAC rooms.view; unknown room 404, cross-property 403.
A54: 1 | B54: 50 | C54: US-011-02 | D54: Complete the primary Room Details workflow | E54: EPIC-05 | F54: Property & Rooms | G54: Room Details | H54: SCR-011 | I54: Room Details | J54: Primary Workflow | K54: Property Admin | L54: As a Property Admin, I want to list, search, filter, view, create, edit, cancel/delete under policy, export in Room Details, so that the room details process is completed accurately without duplicate or inconsistent records. | M54: Enable property & rooms users to manage room details through the Room Details workflow with real-time status, validations and traceability. | N54: View access confirmed; required masters and linked records exist; Administration services are available; approval limit is valid. | O54: Given required fields and valid dependent records, when I submit the primary action, then mandatory, conflict, availability and status-transition rules run before save. Given validation passes, when I confirm, then the transaction is committed exactly once, a success reference is returned and related screens refresh consistently. Given the screen requirement, when tested end to end, then this outcome is met: Authorized users can complete the primary room details workflow; invalid or conflicting actions are blocked with clear messages; saved changes appear in related screens; sensitive changes are auditable. | P54: Duplicate submission is idempotent; stale data returns a refresh/conflict message; invalid status transitions are blocked; partial failure rolls back without orphan records. | Q54: Tenant/property scope; required fields; optimistic locking; timezone-safe dates; reason mandatory for overrides; valid status transition; linked-record integrity | R54: Administration | S54: GET, POST, PUT/PATCH, DELETE /api/v1/room-details; lookup, validation and audit endpoints; idempotency for financial/booking writes; entities: properties, buildings, floors, room_types, rooms, amenities | T54: Must Have | U54: MVP | V54: 5 | W54: S03-S04 | X54: Done | Y54: =IF(X54="Done",1,IF(X54="QA",0.9,IF(X54="Code Review",0.75,IF(X54="In Development",0.5,IF(X54="Ready",0.1,0))))) | AA54: TC-011-B | AB54: Approved screen design; story reviewed with Property Admin; dependencies, API contract, role permissions and test data identified. | AC54: Code reviewed; unit, API, UI, RBAC and integration tests pass; accessibility and responsive states verified; audit evidence captured; product owner accepts in staging. | AD54: Six tabs, each reading the record that already owns the data rather than a second copy: Overview (room + amenities), Reservations (GET /rooms/{id}/reservations - every unit assigned to the room, newest first), Housekeeping and Activity Log (the 064 status timeline, the former narrowed to clean/dirty/cleaning/inspected), Maintenance (GET /rooms/{id}/maintenance - blocks held against the room). Charges is an explicit empty state: folio and billing are not built, and the tab says so rather than showing invented figures. VERIFIED live on rooms 101 and 106, all six tabs. Upcoming Booking verified by temporarily assigning unit CBR24107 to room 101: panel showed the number, Sun 06 Sep -> Wed 09 Sep 2026, 3 nights, 2 adults, Confirmed, and room status moved Available -> Reserved. Assignment then reverted.
A55: 1 | B55: 51 | C55: US-011-03 | D55: Control permissions, overrides and audit for Room Details | E55: EPIC-05 | F55: Property & Rooms | G55: Room Details | H55: SCR-011 | I55: Room Details | J55: Security / Exceptions | K55: Property Admin | L55: As a department supervisor or auditor, I want sensitive actions in Room Details to follow permissions, approval limits and audit rules, so that resort operations remain secure, compliant and traceable. | M55: Reduces fraud, privacy leakage, unauthorized overrides and unresolved operational disputes. | N55: Roles, permissions, approval hierarchy and audit service are configured; allowed and denied test users exist. | O55: Given a user lacks permission, when a restricted UI action or direct API request is attempted, then access is denied without exposing protected data. Given an override, delete, reversal, merge, cancellation or approval-sensitive action, when confirmed, then reason and approval evidence are captured before processing. Given a sensitive action succeeds or fails, when audit history is reviewed, then actor, property, timestamp, before/after values, reason and correlation ID are available. | P55: Tampered IDs, expired sessions, approval-limit violations and cross-tenant requests are rejected; secrets and sensitive guest/payment fields are never written to logs. | Q55: Tenant/property scope; required fields; optimistic locking; timezone-safe dates; reason mandatory for overrides; valid status transition; linked-record integrity | R55: Administration | S55: GET, POST, PUT/PATCH, DELETE /api/v1/room-details; lookup, validation and audit endpoints; idempotency for financial/booking writes; entities: properties, buildings, floors, room_types, rooms, amenities | T55: Must Have | U55: MVP | V55: 3 | W55: S03-S04 | X55: Done | Y55: =IF(X55="Done",1,IF(X55="QA",0.9,IF(X55="Code Review",0.75,IF(X55="In Development",0.5,IF(X55="Ready",0.1,0))))) | AA55: TC-011-C | AB55: Approved screen design; story reviewed with Property Admin; dependencies, API contract, role permissions and test data identified. | AC55: Code reviewed; unit, API, UI, RBAC and integration tests pass; accessibility and responsive states verified; audit evidence captured; product owner accepts in staging. | AD55: Actions delegate to the screens that own them: Edit Room -> 059, Block Room and Mark Out of Order -> the 063 block API. The block dialog was extracted from screen 008 into components/BlockDialog.tsx and is now shared by both screens, so a block raised from either place applies the same rules. VERIFIED: blocking room 101 while it held a reservation was refused by the GiST exclusion constraint and the dialog showed 'Room 101 is already reserved or blocked between 2026-09-08 and 2026-09-08' instead of closing; blocking free room 106 moved it Available -> Out of Order and swapped the button to Release Block with Mark Out of Order disabled; releasing returned it to Available and left the episode on the Maintenance tab as 'ended'. Status chips are colour- and icon-coded per state so a blocked room can never render as a green tick. Read-only screen: no write endpoint added. RBAC rooms.view on all three endpoints (401 anonymous, 403 without permission, 403 cross-property, 404 unknown room).
A56: 1 | B56: 52 | C56: US-024-01 | D56: View and find information in Channel Manager | E56: EPIC-18 | F56: Distribution | G56: Channel Manager | H56: SCR-024 | I56: Channel Manager | J56: View / Search | K56: Revenue Manager | L56: As a Revenue Manager, I want to open Channel Manager and find relevant records using search, filters and sorting, so that I can make accurate operational decisions. | M56: Provides timely visibility for channel manager and reduces manual lookup effort. | N56: Authenticated user; active property; view permission for Distribution; Rates, Rooms, Reservations data available. | O56: Given I am authenticated as Revenue Manager with access to the selected property, when I open Channel Manager, then only permitted tenant/property data is displayed. Given matching records exist, when I search, filter or sort, then results, totals and pagination match the selected criteria. Given no records or a recoverable error, when the screen loads, then a clear empty/error state and safe retry action are shown. | P56: Cross-property data never appears; unauthorized fields are masked; invalid filters do not break the screen; unavailable services return a controlled message. | Q56: Tenant/property scope; required fields; optimistic locking; timezone-safe dates; reason mandatory for overrides; valid status transition; linked-record integrity | R56: Rates, Rooms, Reservations | S56: GET, POST, PUT/PATCH, DELETE /api/v1/channel-manager; lookup, validation and audit endpoints; idempotency for financial/booking writes; entities: channels, channel_mappings, sync_jobs, restrictions | T56: Must Have | U56: MVP | V56: 3 | W56: S03-S04 | X56: Backlog | Y56: =IF(X56="Done",1,IF(X56="QA",0.9,IF(X56="Code Review",0.75,IF(X56="In Development",0.5,IF(X56="Ready",0.1,0))))) | AA56: TC-024-A | AB56: Approved screen design; story reviewed with Revenue Manager; dependencies, API contract, role permissions and test data identified. | AC56: Code reviewed; unit, API, UI, RBAC and integration tests pass; accessibility and responsive states verified; audit evidence captured; product owner accepts in staging.
A57: 1 | B57: 53 | C57: US-024-02 | D57: Complete the primary Channel Manager workflow | E57: EPIC-18 | F57: Distribution | G57: Channel Manager | H57: SCR-024 | I57: Channel Manager | J57: Primary Workflow | K57: Revenue Manager | L57: As a Revenue Manager, I want to list, search, filter, view, create, edit, cancel/delete under policy, export in Channel Manager, so that the channel manager process is completed accurately without duplicate or inconsistent records. | M57: Enable distribution users to manage channel manager through the Channel Manager workflow with real-time status, validations and traceability. | N57: View access confirmed; required masters and linked records exist; Rates, Rooms, Reservations services are available; approval limit is valid. | O57: Given required fields and valid dependent records, when I submit the primary action, then mandatory, conflict, availability and status-transition rules run before save. Given validation passes, when I confirm, then the transaction is committed exactly once, a success reference is returned and related screens refresh consistently. Given the screen requirement, when tested end to end, then this outcome is met: Authorized users can complete the primary channel manager workflow; invalid or conflicting actions are blocked with clear messages; saved changes appear in related screens; sensitive changes are auditable. | P57: Duplicate submission is idempotent; stale data returns a refresh/conflict message; invalid status transitions are blocked; partial failure rolls back without orphan records. | Q57: Tenant/property scope; required fields; optimistic locking; timezone-safe dates; reason mandatory for overrides; valid status transition; linked-record integrity | R57: Rates, Rooms, Reservations | S57: GET, POST, PUT/PATCH, DELETE /api/v1/channel-manager; lookup, validation and audit endpoints; idempotency for financial/booking writes; entities: channels, channel_mappings, sync_jobs, restrictions | T57: Must Have | U57: MVP | V57: 8 | W57: S03-S04 | X57: Backlog | Y57: =IF(X57="Done",1,IF(X57="QA",0.9,IF(X57="Code Review",0.75,IF(X57="In Development",0.5,IF(X57="Ready",0.1,0))))) | AA57: TC-024-B | AB57: Approved screen design; story reviewed with Revenue Manager; dependencies, API contract, role permissions and test data identified. | AC57: Code reviewed; unit, API, UI, RBAC and integration tests pass; accessibility and responsive states verified; audit evidence captured; product owner accepts in staging.
A58: 1 | B58: 54 | C58: US-024-03 | D58: Control permissions, overrides and audit for Channel Manager | E58: EPIC-18 | F58: Distribution | G58: Channel Manager | H58: SCR-024 | I58: Channel Manager | J58: Security / Exceptions | K58: Revenue Manager | L58: As a department supervisor or auditor, I want sensitive actions in Channel Manager to follow permissions, approval limits and audit rules, so that resort operations remain secure, compliant and traceable. | M58: Reduces fraud, privacy leakage, unauthorized overrides and unresolved operational disputes. | N58: Roles, permissions, approval hierarchy and audit service are configured; allowed and denied test users exist. | O58: Given a user lacks permission, when a restricted UI action or direct API request is attempted, then access is denied without exposing protected data. Given an override, delete, reversal, merge, cancellation or approval-sensitive action, when confirmed, then reason and approval evidence are captured before processing. Given a sensitive action succeeds or fails, when audit history is reviewed, then actor, property, timestamp, before/after values, reason and correlation ID are available. | P58: Tampered IDs, expired sessions, approval-limit violations and cross-tenant requests are rejected; secrets and sensitive guest/payment fields are never written to logs. | Q58: Tenant/property scope; required fields; optimistic locking; timezone-safe dates; reason mandatory for overrides; valid status transition; linked-record integrity | R58: Rates, Rooms, Reservations | S58: GET, POST, PUT/PATCH, DELETE /api/v1/channel-manager; lookup, validation and audit endpoints; idempotency for financial/booking writes; entities: channels, channel_mappings, sync_jobs, restrictions | T58: Must Have | U58: MVP | V58: 5 | W58: S03-S04 | X58: Backlog | Y58: =IF(X58="Done",1,IF(X58="QA",0.9,IF(X58="Code Review",0.75,IF(X58="In Development",0.5,IF(X58="Ready",0.1,0))))) | AA58: TC-024-C | AB58: Approved screen design; story reviewed with Revenue Manager; dependencies, API contract, role permissions and test data identified. | AC58: Code reviewed; unit, API, UI, RBAC and integration tests pass; accessibility and responsive states verified; audit evidence captured; product owner accepts in staging.
A59: 1 | B59: 55 | C59: US-033-01 | D59: View and find information in Rate Plans | E59: EPIC-22 | F59: Revenue Management | G59: Rate Plans | H59: SCR-033 | I59: Rate Plans | J59: View / Search | K59: Revenue Manager | L59: As a Revenue Manager, I want to open Rate Plans and find relevant records using search, filters and sorting, so that I can make accurate operational decisions. | M59: Provides timely visibility for rate plans and reduces manual lookup effort. | N59: Authenticated user; active property; view permission for Revenue Management; Rooms, Distribution, Reservations data available. | O59: Given I am authenticated as Revenue Manager with access to the selected property, when I open Rate Plans, then only permitted tenant/property data is displayed. Given matching records exist, when I search, filter or sort, then results, totals and pagination match the selected criteria. Given no records or a recoverable error, when the screen loads, then a clear empty/error state and safe retry action are shown. | P59: Cross-property data never appears; unauthorized fields are masked; invalid filters do not break the screen; unavailable services return a controlled message. | Q59: Tenant/property scope; required fields; optimistic locking; timezone-safe dates; reason mandatory for overrides; currency precision; tax/rate totals; approval limit; no unbalanced or duplicate posting | R59: Rooms, Distribution, Reservations | S59: GET, POST, PUT/PATCH, DELETE /api/v1/rate-plans; lookup, validation and audit endpoints; idempotency for financial/booking writes; entities: rate_plans, rate_rules, packages, restrictions, inventory_controls | T59: Must Have | U59: MVP | V59: 3 | W59: S03-S04 | X59: Done | Y59: =IF(X59="Done",1,IF(X59="QA",0.9,IF(X59="Code Review",0.75,IF(X59="In Development",0.5,IF(X59="Ready",0.1,0))))) | AA59: TC-033-A | AB59: Approved screen design; story reviewed with Revenue Manager; dependencies, API contract, role permissions and test data identified. | AC59: Code reviewed; unit, API, UI, RBAC and integration tests pass; accessibility and responsive states verified; audit evidence captured; product owner accepts in staging. | AD59: Rate Plans (mockup 033) at /rates, plus the previously-empty Rate Plans tab on Rooms & Villas (008) which now renders the same component with its page heading suppressed. New sidebar item 'Rates'. Migration 0010 adds property.meal_plans, property.rate_plans and property.rate_plan_room_types. KEY MODELLING DECISION: a rate plan stores an ADJUSTMENT to the room type's base rate, never a price of its own, so the 'From' figure on each card is computed in SQL on read and changing a room type's base rate moves every plan built on it - there is no second copy of the price to go stale. VERIFIED: base 6500 -> BAR +0% = 6500, BB +15% = 7475, FLEX +8% = 7020, CORP -8% = 5980, NRF -15% = 5525; editing BAR to +12% through the UI moved it to 7280 and back to 6500 on revert. Cards show name, short code, description, cancellation chip, meal plan, guest range, From price, Active badge and an actions menu. All four filters (search, status, meal plan, room type) verified. RBAC rooms.view. FIXED PRICE: a plan can either adjust the room type rate or carry a fixed nightly price (migration 0013, nullable flat_rate where NULL means 'follow the room type'). The drawer offers both as a toggle. DEFECT FIXED: an adjustment-priced plan read only room_types.base_rate and ignored per-date rates set on the Rates & Inventory calendar, so it quoted the wrong price on any repriced night. It now prices off the effective nightly rate - the calendar rate where one exists, the base rate otherwise - taking the lowest across the next 90 days. VERIFIED: pricing 20 Sep at 4000 moved CORP from 5980 to 3680 and NRF from 5525 to 3400; clearing it restored both.
A60: 1 | B60: 56 | C60: US-033-02 | D60: Complete the primary Rate Plans workflow | E60: EPIC-22 | F60: Revenue Management | G60: Rate Plans | H60: SCR-033 | I60: Rate Plans | J60: Primary Workflow | K60: Revenue Manager | L60: As a Revenue Manager, I want to list, search, filter, view, create, edit, cancel/delete under policy, export in Rate Plans, so that the rate plans process is completed accurately without duplicate or inconsistent records. | M60: Enable revenue management users to manage rate plans through the Rate Plans workflow with real-time status, validations and traceability. | N60: View access confirmed; required masters and linked records exist; Rooms, Distribution, Reservations services are available; approval limit is valid. | O60: Given required fields and valid dependent records, when I submit the primary action, then mandatory, conflict, availability and status-transition rules run before save. Given validation passes, when I confirm, then the transaction is committed exactly once, a success reference is returned and related screens refresh consistently. Given the screen requirement, when tested end to end, then this outcome is met: Authorized users can complete the primary rate plans workflow; invalid or conflicting actions are blocked with clear messages; saved changes appear in related screens; sensitive changes are auditable. | P60: Duplicate submission is idempotent; stale data returns a refresh/conflict message; invalid status transitions are blocked; partial failure rolls back without orphan records. | Q60: Tenant/property scope; required fields; optimistic locking; timezone-safe dates; reason mandatory for overrides; currency precision; tax/rate totals; approval limit; no unbalanced or duplicate posting | R60: Rooms, Distribution, Reservations | S60: GET, POST, PUT/PATCH, DELETE /api/v1/rate-plans; lookup, validation and audit endpoints; idempotency for financial/booking writes; entities: rate_plans, rate_rules, packages, restrictions, inventory_controls | T60: Must Have | U60: MVP | V60: 8 | W60: S03-S04 | X60: Done | Y60: =IF(X60="Done",1,IF(X60="QA",0.9,IF(X60="Code Review",0.75,IF(X60="In Development",0.5,IF(X60="Ready",0.1,0))))) | AA60: TC-033-B | AB60: Approved screen design; story reviewed with Revenue Manager; dependencies, API contract, role permissions and test data identified. | AC60: Code reviewed; unit, API, UI, RBAC and integration tests pass; accessibility and responsive states verified; audit evidence captured; product owner accepts in staging. | AD60: Four tabs. Rate Plans is the full CRUD. Meal Plans is a real master (RO/BB/HB/FB/AI seeded) because the rate plan form selects one; a meal plan in use by an active rate plan cannot be deactivated (409 naming the count). Corporate Rates is the SAME list filtered to plan_type='corporate' rather than a second entity - the mockup shows 'Corporate BlueWave' among the ordinary plans, so a separate record would mean storing it twice. Taxes is an explicit empty state pointing at screen 118 (Tax and Service Charge Setup), which is not built. Edit drawer matches the mockup: name, short code, description, Base Rate Adjustment with Increase/Decrease + value + %/INR toggle, meal plan, extra adult and child charges, minimum stay, guest range, cancellation policy, Refundable checkbox, plan type, corporate account, room-type scoping (none selected = all room types) and a single image with upload/replace/remove. Duplicate produces '<CODE>-2', '-3' and starts inactive so a copy cannot be sold before review.
A61: 1 | B61: 57 | C61: US-033-03 | D61: Control permissions, overrides and audit for Rate Plans | E61: EPIC-22 | F61: Revenue Management | G61: Rate Plans | H61: SCR-033 | I61: Rate Plans | J61: Security / Exceptions | K61: Revenue Manager | L61: As a department supervisor or auditor, I want sensitive actions in Rate Plans to follow permissions, approval limits and audit rules, so that resort operations remain secure, compliant and traceable. | M61: Reduces fraud, privacy leakage, unauthorized overrides and unresolved operational disputes. | N61: Roles, permissions, approval hierarchy and audit service are configured; allowed and denied test users exist. | O61: Given a user lacks permission, when a restricted UI action or direct API request is attempted, then access is denied without exposing protected data. Given an override, delete, reversal, merge, cancellation or approval-sensitive action, when confirmed, then reason and approval evidence are captured before processing. Given a sensitive action succeeds or fails, when audit history is reviewed, then actor, property, timestamp, before/after values, reason and correlation ID are available. | P61: Tampered IDs, expired sessions, approval-limit violations and cross-tenant requests are rejected; secrets and sensitive guest/payment fields are never written to logs. | Q61: Tenant/property scope; required fields; optimistic locking; timezone-safe dates; reason mandatory for overrides; currency precision; tax/rate totals; approval limit; no unbalanced or duplicate posting | R61: Rooms, Distribution, Reservations | S61: GET, POST, PUT/PATCH, DELETE /api/v1/rate-plans; lookup, validation and audit endpoints; idempotency for financial/booking writes; entities: rate_plans, rate_rules, packages, restrictions, inventory_controls | T61: Must Have | U61: MVP | V61: 5 | W61: S03-S04 | X61: Done | Y61: =IF(X61="Done",1,IF(X61="QA",0.9,IF(X61="Code Review",0.75,IF(X61="In Development",0.5,IF(X61="Ready",0.1,0))))) | AA61: TC-033-C | AB61: Approved screen design; story reviewed with Revenue Manager; dependencies, API contract, role permissions and test data identified. | AC61: Code reviewed; unit, API, UI, RBAC and integration tests pass; accessibility and responsive states verified; audit evidence captured; product owner accepts in staging. | AD61: Optimistic locking on version (stale -> 409). Duplicate code -> 409. Audit on create/update/activate/deactivate/duplicate/image. Plans are deactivated, never deleted, because past reservations were sold on their terms. VALIDATION verified, all 422 with a sentence naming the field: percentage discount over 100%, negative adjustment, min_stay 0, max guests below min, non-refundable plan carrying free-cancellation hours, corporate plan with no account, invalid plan_type, negative child charge, room type from another property. The same rules exist as CHECK constraints so the database is the backstop. Composite FKs on (property_id, id) for meal plan and room type links prevent cross-property references. Image upload accepts JPG/PNG/WebP only (text/plain -> 422) and the object is removed from MinIO on delete. RBAC: 401 anonymous, 403 without rooms.view/create/edit, 403 cross-property.
A62: 1 | B62: 58 | C62: US-034-01 | D62: View and find information in Rates Restrictions and Inventory Calendar | E62: EPIC-22 | F62: Revenue Management | G62: Rates & Restrictions | H62: SCR-034 | I62: Rates Restrictions and Inventory Calendar | J62: View / Search | K62: Revenue Manager | L62: As a Revenue Manager, I want to open Rates Restrictions and Inventory Calendar and find relevant records using search, filters and sorting, so that I can make accurate operational decisions. | M62: Provides timely visibility for rates & restrictions and reduces manual lookup effort. | N62: Authenticated user; active property; view permission for Revenue Management; Rooms, Distribution, Reservations data available. | O62: Given I am authenticated as Revenue Manager with access to the selected property, when I open Rates Restrictions and Inventory Calendar, then only permitted tenant/property data is displayed. Given matching records exist, when I search, filter or sort, then results, totals and pagination match the selected criteria. Given no records or a recoverable error, when the screen loads, then a clear empty/error state and safe retry action are shown. | P62: Cross-property data never appears; unauthorized fields are masked; invalid filters do not break the screen; unavailable services return a controlled message. | Q62: Tenant/property scope; required fields; optimistic locking; timezone-safe dates; reason mandatory for overrides; currency precision; tax/rate totals; approval limit; no unbalanced or duplicate posting | R62: Rooms, Distribution, Reservations | S62: GET, POST, PUT/PATCH, DELETE /api/v1/rates-restrictions-and-inventory-calendar; lookup, validation and audit endpoints; idempotency for financial/booking writes; entities: rate_plans, rate_rules, packages, restrictions, inventory_controls | T62: Must Have | U62: MVP | V62: 3 | W62: S03-S04 | X62: Done | Y62: =IF(X62="Done",1,IF(X62="QA",0.9,IF(X62="Code Review",0.75,IF(X62="In Development",0.5,IF(X62="Ready",0.1,0))))) | AA62: TC-034-A | AB62: Approved screen design; story reviewed with Revenue Manager; dependencies, API contract, role permissions and test data identified. | AC62: Code reviewed; unit, API, UI, RBAC and integration tests pass; accessibility and responsive states verified; audit evidence captured; product owner accepts in staging. | AD62: Rates & Inventory (mockup 034) at /rates/calendar. Rates is now an expandable sidebar group holding Rate Plans (033) and Rates & Inventory (034), as planned when it gained a second screen; /rates redirects to /rates/plans. Migration 0011 adds property.rate_calendar_days, deliberately SPARSE: a row exists only where a date has been overridden, and rate and min_stay are nullable so NULL means 'inherit from the room type' rather than a value that happens to match. A new room type is therefore sellable on every date with no rows, and changing base_rate still moves every untouched date. Grid: one row group per room type (Rate / Available / Min Stay / Stop Sell as four aligned table rows via rowSpan), date columns with weekend tinting, and an Occupancy Forecast row. Overridden cells are visually marked so it is always clear which figures were set by hand. Window capped at 60 days (422 beyond that, and on a backwards range). RATE PLAN VIEW: the toolbar has a plan selector alongside the room type filter. Choosing a plan re-prices every cell as that plan sells it - its flat rate, or the room type's effective rate carrying its adjustment - using the same arithmetic as the plan's headline price, so the two screens cannot disagree. The grid is read-only in that view (rate boxes, min stay, stop sell, date selection, Bulk Update and Copy Rates all disabled) because the figure is derived, with a banner saying so. VERIFIED: room type 6500 -> Best Available Rate (flat 3000) showed 3000; Corporate BlueWave (-8%) showed 5980, and 6578 after the room type was raised to 7150. Unknown plan -> 404. Clearing a cell's last value now deletes the row, so the table keeps meaning 'overrides only'.
A63: 1 | B63: 59 | C63: US-034-02 | D63: Complete the primary Rates Restrictions and Inventory Calendar workflow | E63: EPIC-22 | F63: Revenue Management | G63: Rates & Restrictions | H63: SCR-034 | I63: Rates Restrictions and Inventory Calendar | J63: Primary Workflow | K63: Revenue Manager | L63: As a Revenue Manager, I want to view timeline, filter, create, assign, reschedule, conflict-check, cancel in Rates Restrictions and Inventory Calendar, so that the rates & restrictions process is completed accurately without duplicate or inconsistent records. | M63: Enable revenue management users to manage rates & restrictions through the Rates Restrictions and Inventory Calendar workflow with real-time status, validations and traceability. | N63: View access confirmed; required masters and linked records exist; Rooms, Distribution, Reservations services are available; approval limit is valid. | O63: Given required fields and valid dependent records, when I submit the primary action, then mandatory, conflict, availability and status-transition rules run before save. Given validation passes, when I confirm, then the transaction is committed exactly once, a success reference is returned and related screens refresh consistently. Given the screen requirement, when tested end to end, then this outcome is met: Authorized users can complete the primary rates restrictions and inventory calendar workflow; invalid or conflicting actions are blocked with clear messages; saved changes appear in related screens; sensitive changes are auditable. | P63: Duplicate submission is idempotent; stale data returns a refresh/conflict message; invalid status transitions are blocked; partial failure rolls back without orphan records. | Q63: Tenant/property scope; required fields; optimistic locking; timezone-safe dates; reason mandatory for overrides; currency precision; tax/rate totals; approval limit; no unbalanced or duplicate posting | R63: Rooms, Distribution, Reservations | S63: GET, POST, PUT/PATCH, DELETE /api/v1/rates-restrictions-and-inventory-calendar; lookup, validation and audit endpoints; idempotency for financial/booking writes; entities: rate_plans, rate_rules, packages, restrictions, inventory_controls | T63: Must Have | U63: MVP | V63: 8 | W63: S03-S04 | X63: Done | Y63: =IF(X63="Done",1,IF(X63="QA",0.9,IF(X63="Code Review",0.75,IF(X63="In Development",0.5,IF(X63="Ready",0.1,0))))) | AA63: TC-034-B | AB63: Approved screen design; story reviewed with Revenue Manager; dependencies, API contract, role permissions and test data identified. | AC63: Code reviewed; unit, API, UI, RBAC and integration tests pass; accessibility and responsive states verified; audit evidence captured; product owner accepts in staging. | AD63: Availability is DERIVED at read time, never stored: capacity is the live count of active rooms of that type, minus rooms with an active block covering the date, minus reserved/held/allotment from booking.room_type_inventory_days (which the booking path owns). VERIFIED against ground truth: room 102 blocked on 2026-09-08 gave Deluxe Sea View 43 available that day and 44 on every other, and the block is the only active one in the property. Caught and fixed a real bug here: generate_series over dates yields timestamps, so the blocked-rooms lookup keyed by date silently matched nothing and availability ignored blocks entirely. Inline editing verified live: typing 5555 into a cell set an override, clearing the box removed it and the cell fell back to the room type's 6500, and the stop-sell switch toggled. Selects are blurred on wheel so a stray scroll over the dense grid cannot silently write a restriction.
A64: 1 | B64: 60 | C64: US-034-03 | D64: Control permissions, overrides and audit for Rates Restrictions and Inventory Calendar | E64: EPIC-22 | F64: Revenue Management | G64: Rates & Restrictions | H64: SCR-034 | I64: Rates Restrictions and Inventory Calendar | J64: Security / Exceptions | K64: Revenue Manager | L64: As a department supervisor or auditor, I want sensitive actions in Rates Restrictions and Inventory Calendar to follow permissions, approval limits and audit rules, so that resort operations remain secure, compliant and traceable. | M64: Reduces fraud, privacy leakage, unauthorized overrides and unresolved operational disputes. | N64: Roles, permissions, approval hierarchy and audit service are configured; allowed and denied test users exist. | O64: Given a user lacks permission, when a restricted UI action or direct API request is attempted, then access is denied without exposing protected data. Given an override, delete, reversal, merge, cancellation or approval-sensitive action, when confirmed, then reason and approval evidence are captured before processing. Given a sensitive action succeeds or fails, when audit history is reviewed, then actor, property, timestamp, before/after values, reason and correlation ID are available. | P64: Tampered IDs, expired sessions, approval-limit violations and cross-tenant requests are rejected; secrets and sensitive guest/payment fields are never written to logs. | Q64: Tenant/property scope; required fields; optimistic locking; timezone-safe dates; reason mandatory for overrides; currency precision; tax/rate totals; approval limit; no unbalanced or duplicate posting | R64: Rooms, Distribution, Reservations | S64: GET, POST, PUT/PATCH, DELETE /api/v1/rates-restrictions-and-inventory-calendar; lookup, validation and audit endpoints; idempotency for financial/booking writes; entities: rate_plans, rate_rules, packages, restrictions, inventory_controls | T64: Must Have | U64: MVP | V64: 5 | W64: S03-S04 | X64: Done | Y64: =IF(X64="Done",1,IF(X64="QA",0.9,IF(X64="Code Review",0.75,IF(X64="In Development",0.5,IF(X64="Ready",0.1,0))))) | AA64: TC-034-C | AB64: Approved screen design; story reviewed with Revenue Manager; dependencies, API contract, role permissions and test data identified. | AC64: Code reviewed; unit, API, UI, RBAC and integration tests pass; accessibility and responsive states verified; audit evidence captured; product owner accepts in staging. | AD64: The right-hand panel previews and publishes through the SAME request; only preview_only differs, so what the panel promises is what the button does. VERIFIED live end to end: selecting 12-13 Sep (Sat/Sun) and previewing +10% showed Current 6,500 -> New 7,150 per room type and 'will update rates for 4 room types across 2 dates (8 rate cells)' while the grid stayed at 6,500; publishing moved the grid to 7,150 and reported 'Published. 8 rate cells updated.' Bulk can also set min stay and stop sell in the same pass. Copy Rates copies a window forward day by day and refuses an overlapping target (422). Validation, all 422: percentage decrease over 100, negative value, unknown change mode, min stay 0, stop sell with no value, room type outside the property, negative rate, backwards range, window over 60 days. Audit on cell update, bulk update and copy. Yield Rules and Sync Channels are honest notices pointing at screens 119 and 024/120, which are not built. RBAC rooms.view to read, rooms.edit to write (401 anonymous, 403 otherwise).
A65: 1 | B65: 61 | C65: US-035-01 | D65: View and find information in Packages and Promotions | E65: EPIC-22 | F65: Revenue Management | G65: Offers | H65: SCR-035 | I65: Packages and Promotions | J65: View / Search | K65: Revenue Manager | L65: As a Revenue Manager, I want to open Packages and Promotions and find relevant records using search, filters and sorting, so that I can make accurate operational decisions. | M65: Provides timely visibility for offers and reduces manual lookup effort. | N65: Authenticated user; active property; view permission for Revenue Management; Rooms, Distribution, Reservations data available. | O65: Given I am authenticated as Revenue Manager with access to the selected property, when I open Packages and Promotions, then only permitted tenant/property data is displayed. Given matching records exist, when I search, filter or sort, then results, totals and pagination match the selected criteria. Given no records or a recoverable error, when the screen loads, then a clear empty/error state and safe retry action are shown. | P65: Cross-property data never appears; unauthorized fields are masked; invalid filters do not break the screen; unavailable services return a controlled message. | Q65: Tenant/property scope; required fields; optimistic locking; timezone-safe dates; reason mandatory for overrides; currency precision; tax/rate totals; approval limit; no unbalanced or duplicate posting | R65: Rooms, Distribution, Reservations | S65: GET, POST, PUT/PATCH, DELETE /api/v1/packages-and-promotions; lookup, validation and audit endpoints; idempotency for financial/booking writes; entities: rate_plans, rate_rules, packages, restrictions, inventory_controls | T65: Must Have | U65: MVP | V65: 3 | W65: S03-S04 | X65: Done | Y65: =IF(X65="Done",1,IF(X65="QA",0.9,IF(X65="Code Review",0.75,IF(X65="In Development",0.5,IF(X65="Ready",0.1,0))))) | AA65: TC-035-A | AB65: Approved screen design; story reviewed with Revenue Manager; dependencies, API contract, role permissions and test data identified. | AC65: Code reviewed; unit, API, UI, RBAC and integration tests pass; accessibility and responsive states verified; audit evidence captured; product owner accepts in staging. | AD65: Packages & Promotions (mockup 035) at /rates/packages, third item under the Rates group. Migration 0012 adds property.packages, package_inclusions, package_room_types, addons, promo_codes and promo_redemptions. KEY DECISION: a package prices exactly like a rate plan - it holds an ADJUSTMENT to the room type's base rate, never a price of its own - so the headline 'From' figure is computed and cannot drift from the room it is built on. VERIFIED on the seeded demo packages against the 6500 base: Monsoon Escape +8% = 7020, Corporate Retreat +15% = 7475, Family Weekend +30% = 8450, Honeymoon Bliss +100% = 13000. Featured cards match the mockup: image with optional badge overlay, name, tagline, validity window, From price, tick-listed inclusions, and a Bookings / Revenue / status footer. Room-type scoping follows the same convention as rate plans - selecting none means every room type. RBAC rooms.view. FIXED PRICE: packages take the same flat_rate option as rate plans (migration 0013) with the same toggle in the dialog. The same base-rate defect was fixed here: a package now prices off the effective nightly rate over its own validity window rather than the static base rate. VERIFIED: pricing 20 Sep at 4000 moved Monsoon Escape (+8%) from 7020 to 4320.
A66: 1 | B66: 62 | C66: US-035-02 | D66: Complete the primary Packages and Promotions workflow | E66: EPIC-22 | F66: Revenue Management | G66: Offers | H66: SCR-035 | I66: Packages and Promotions | J66: Primary Workflow | K66: Revenue Manager | L66: As a Revenue Manager, I want to list, search, filter, view, create, edit, cancel/delete under policy, export in Packages and Promotions, so that the offers process is completed accurately without duplicate or inconsistent records. | M66: Enable revenue management users to manage offers through the Packages and Promotions workflow with real-time status, validations and traceability. | N66: View access confirmed; required masters and linked records exist; Rooms, Distribution, Reservations services are available; approval limit is valid. | O66: Given required fields and valid dependent records, when I submit the primary action, then mandatory, conflict, availability and status-transition rules run before save. Given validation passes, when I confirm, then the transaction is committed exactly once, a success reference is returned and related screens refresh consistently. Given the screen requirement, when tested end to end, then this outcome is met: Authorized users can complete the primary packages and promotions workflow; invalid or conflicting actions are blocked with clear messages; saved changes appear in related screens; sensitive changes are auditable. | P66: Duplicate submission is idempotent; stale data returns a refresh/conflict message; invalid status transitions are blocked; partial failure rolls back without orphan records. | Q66: Tenant/property scope; required fields; optimistic locking; timezone-safe dates; reason mandatory for overrides; currency precision; tax/rate totals; approval limit; no unbalanced or duplicate posting | R66: Rooms, Distribution, Reservations | S66: GET, POST, PUT/PATCH, DELETE /api/v1/packages-and-promotions; lookup, validation and audit endpoints; idempotency for financial/booking writes; entities: rate_plans, rate_rules, packages, restrictions, inventory_controls | T66: Must Have | U66: MVP | V66: 8 | W66: S03-S04 | X66: Done | Y66: =IF(X66="Done",1,IF(X66="QA",0.9,IF(X66="Code Review",0.75,IF(X66="In Development",0.5,IF(X66="Ready",0.1,0))))) | AA66: TC-035-B | AB66: Approved screen design; story reviewed with Revenue Manager; dependencies, API contract, role permissions and test data identified. | AC66: Code reviewed; unit, API, UI, RBAC and integration tests pass; accessibility and responsive states verified; audit evidence captured; product owner accepts in staging. | AD66: Four tabs. Packages is the full CRUD with a card image (upload/replace/remove) and up to 20 inclusions; an inclusion can point at a real add-on so its name and price live in one place, or stay free text for something the property does not stock such as a late check-out. Add-ons is a master in its own right (code, category, price, pricing unit) showing how many packages use each. Promo Codes is the mockup's table - Code, Description, Usage, Usage Limit, Value, Expiry, Status, Actions - with a derived state badge that combines status, dates and usage: Active, Inactive, Scheduled, Expired or Limit reached. Redemption is the live log. VERIFIED live through the UI: redeeming BAY10 for 'Priya Sharma' incremented usage and appeared on the Redemption tab attributed to Kishore Admin with a timestamp.
A67: 1 | B67: 63 | C67: US-035-03 | D67: Control permissions, overrides and audit for Packages and Promotions | E67: EPIC-22 | F67: Revenue Management | G67: Offers | H67: SCR-035 | I67: Packages and Promotions | J67: Security / Exceptions | K67: Revenue Manager | L67: As a department supervisor or auditor, I want sensitive actions in Packages and Promotions to follow permissions, approval limits and audit rules, so that resort operations remain secure, compliant and traceable. | M67: Reduces fraud, privacy leakage, unauthorized overrides and unresolved operational disputes. | N67: Roles, permissions, approval hierarchy and audit service are configured; allowed and denied test users exist. | O67: Given a user lacks permission, when a restricted UI action or direct API request is attempted, then access is denied without exposing protected data. Given an override, delete, reversal, merge, cancellation or approval-sensitive action, when confirmed, then reason and approval evidence are captured before processing. Given a sensitive action succeeds or fails, when audit history is reviewed, then actor, property, timestamp, before/after values, reason and correlation ID are available. | P67: Tampered IDs, expired sessions, approval-limit violations and cross-tenant requests are rejected; secrets and sensitive guest/payment fields are never written to logs. | Q67: Tenant/property scope; required fields; optimistic locking; timezone-safe dates; reason mandatory for overrides; currency precision; tax/rate totals; approval limit; no unbalanced or duplicate posting | R67: Rooms, Distribution, Reservations | S67: GET, POST, PUT/PATCH, DELETE /api/v1/packages-and-promotions; lookup, validation and audit endpoints; idempotency for financial/booking writes; entities: rate_plans, rate_rules, packages, restrictions, inventory_controls | T67: Must Have | U67: MVP | V67: 5 | W67: S03-S04 | X67: Done | Y67: =IF(X67="Done",1,IF(X67="QA",0.9,IF(X67="Code Review",0.75,IF(X67="In Development",0.5,IF(X67="Ready",0.1,0))))) | AA67: TC-035-C | AB67: Approved screen design; story reviewed with Revenue Manager; dependencies, API contract, role permissions and test data identified. | AC67: Code reviewed; unit, API, UI, RBAC and integration tests pass; accessibility and responsive states verified; audit evidence captured; product owner accepts in staging. | AD67: Bookings and revenue on a package card are DERIVED from reservation units naming the package (new nullable booking.reservation_units.package_id with a composite FK). The booking flow does not offer packages yet, so both read zero - the truth rather than a decorative number - and become real with no backfill the moment a reservation carries a package. Redemption integrity: the promo row is locked FOR UPDATE and its state re-checked inside the transaction, so two concurrent redemptions cannot both take the last use; every increment writes a matching promo_redemptions row in the same transaction, and a CHECK constraint stops usage_count exceeding the limit. VERIFIED: redeeming an expired code -> 409 'cannot be redeemed: Expired'; redeeming past the limit -> 409 'Limit reached'; lowering a usage limit below what has already been redeemed -> 422 naming the count. Validation, all 422: valid-to before valid-from, discount over 100%, negative adjustment, min nights 0, max below min nights, invalid status, room type or add-on from another property, zero discount, negative usage limit. Optimistic locking (409), duplicate codes (409), unknown package (404). Audit on every create/update/status/image/redeem. RBAC 401/403/403 cross-property.
A68: 1 | B68: 64 | C68: US-058-01 | D68: View and find information in Deposit Schedule | E68: EPIC-16 | F68: Finance | G68: Deposits | H68: SCR-058 | I68: Deposit Schedule | J68: View / Search | K68: Finance Manager | L68: As a Finance Manager, I want to open Deposit Schedule and find relevant records using search, filters and sorting, so that I can make accurate operational decisions. | M68: Provides timely visibility for deposits and reduces manual lookup effort. | N68: Authenticated user; active property; view permission for Finance; All revenue modules data available. | O68: Given I am authenticated as Finance Manager with access to the selected property, when I open Deposit Schedule, then only permitted tenant/property data is displayed. Given matching records exist, when I search, filter or sort, then results, totals and pagination match the selected criteria. Given no records or a recoverable error, when the screen loads, then a clear empty/error state and safe retry action are shown. | P68: Cross-property data never appears; unauthorized fields are masked; invalid filters do not break the screen; unavailable services return a controlled message. | Q68: Tenant/property scope; required fields; optimistic locking; timezone-safe dates; reason mandatory for overrides; currency precision; tax/rate totals; approval limit; no unbalanced or duplicate posting | R68: All revenue modules | S68: GET, POST, PUT/PATCH, DELETE /api/v1/deposit-schedule; lookup, validation and audit endpoints; idempotency for financial/booking writes; entities: folios, payments, refunds, invoices, credit_notes, cash_drawers, taxes, receivables | T68: Must Have | U68: MVP | V68: 3 | W68: S03-S04 | X68: Done | Y68: 1 | AA68: TC-058-A | AB68: Approved screen design; story reviewed with Finance Manager; dependencies, API contract, role permissions and test data identified. | AC68: Code reviewed; unit, API, UI, RBAC and integration tests pass; accessibility and responsive states verified; audit evidence captured; product owner accepts in staging. | AD68: Deposit Schedule (mockup 058) view at /reservations/{id}/deposits: header (guest, occupancy, room type, stay, nights) + tab strip; 5 KPI cards (Total Booking Value, Total Deposit Required + %, Total Received + % of scheduled, Balance Due, Next Due Date with overdue/in-N-days); instalment table (#, instalment + %, amount, due date, status, received on, method, reminder, actions) with paid/balance sub-row per row and a Show cancelled toggle. Booking value is real: booking-core /reservations/{id}/detail now returns booking_value = sum over units of nights x (rate_calendar_days rate, else room type base rate), cancelled units at zero. Verified in Chrome on CBR39535923: 3 nights x 6500 = Rs 19,500.
A69: 1 | B69: 65 | C69: US-058-02 | D69: Complete the primary Deposit Schedule workflow | E69: EPIC-16 | F69: Finance | G69: Deposits | H69: SCR-058 | I69: Deposit Schedule | J69: Primary Workflow | K69: Finance Manager | L69: As a Finance Manager, I want to view timeline, filter, create, assign, reschedule, conflict-check, cancel in Deposit Schedule, so that the deposits process is completed accurately without duplicate or inconsistent records. | M69: Enable finance users to manage deposits through the Deposit Schedule workflow with real-time status, validations and traceability. | N69: View access confirmed; required masters and linked records exist; All revenue modules services are available; approval limit is valid. | O69: Given required fields and valid dependent records, when I submit the primary action, then mandatory, conflict, availability and status-transition rules run before save. Given validation passes, when I confirm, then the transaction is committed exactly once, a success reference is returned and related screens refresh consistently. Given the screen requirement, when tested end to end, then this outcome is met: Authorized users can complete the primary deposit schedule workflow; invalid or conflicting actions are blocked with clear messages; saved changes appear in related screens; sensitive changes are auditable. | P69: Duplicate submission is idempotent; stale data returns a refresh/conflict message; invalid status transitions are blocked; partial failure rolls back without orphan records. | Q69: Tenant/property scope; required fields; optimistic locking; timezone-safe dates; reason mandatory for overrides; currency precision; tax/rate totals; approval limit; no unbalanced or duplicate posting | R69: All revenue modules | S69: GET, POST, PUT/PATCH, DELETE /api/v1/deposit-schedule; lookup, validation and audit endpoints; idempotency for financial/booking writes; entities: folios, payments, refunds, invoices, credit_notes, cash_drawers, taxes, receivables | T69: Must Have | U69: MVP | V69: 8 | W69: S03-S04 | X69: Done | Y69: 1 | AA69: TC-058-B | AB69: Approved screen design; story reviewed with Finance Manager; dependencies, API contract, role permissions and test data identified. | AC69: Code reviewed; unit, API, UI, RBAC and integration tests pass; accessibility and responsive states verified; audit evidence captured; product owner accepts in staging. | AD69: Primary workflow: generate a schedule from percentage splits (20/10/balance-on-arrival), add/edit instalment (fixed amount or % of booking), cancel, collect payment, waive, refund/reverse, and reminder state. Collections go through the SAME finance.post_payment path as every other payment, so each posts a real credit to the reservation folio and appears in Payments; deposit_allocations records which instalment a payment settled. paid_amount is NOT stored - it is SUM(allocations) - so the schedule cannot disagree with the ledger. Status is derived (paid / partially paid / pending / waived); only cancelled is set by a person. Verified in Chrome: collected Rs 1,500 against a Rs 3,900 instalment -> Partially Paid, balance Rs 2,400, Rs 1,500 credit on the folio; waived Rs 1,950 -> Waived, balance moved Rs 18,000 -> Rs 16,050, next due date recalculated; reminder marked sent. [14 Sep 2026 defect sweep] DEFECT FOUND AND FIXED (high). The deposit refund route posted a folio debit and a negative deposit_allocation and never wrote finance.refunds -- the table that decides how much of a payment is still refundable. The same money could therefore be given back a second time through /refunds, which would pass its own check happily. Now recorded, with the caller's open drawer attached when they have one. RESIDUAL, STATED DELIBERATELY: this route does not REQUIRE an open drawer the way /refunds does, because it never has and refusing now would stop a working flow -- so a cash deposit refund can still leave a till with no shift recording it. Two knock-ons fixed: 'deposit_refund' is a different source_type from 'refund', so it was escaping both the ledger-scope classification and folio_money's net-of-refunds calculation.
A70: 1 | B70: 66 | C70: US-058-03 | D70: Control permissions, overrides and audit for Deposit Schedule | E70: EPIC-16 | F70: Finance | G70: Deposits | H70: SCR-058 | I70: Deposit Schedule | J70: Security / Exceptions | K70: Finance Manager | L70: As a department supervisor or auditor, I want sensitive actions in Deposit Schedule to follow permissions, approval limits and audit rules, so that resort operations remain secure, compliant and traceable. | M70: Reduces fraud, privacy leakage, unauthorized overrides and unresolved operational disputes. | N70: Roles, permissions, approval hierarchy and audit service are configured; allowed and denied test users exist. | O70: Given a user lacks permission, when a restricted UI action or direct API request is attempted, then access is denied without exposing protected data. Given an override, delete, reversal, merge, cancellation or approval-sensitive action, when confirmed, then reason and approval evidence are captured before processing. Given a sensitive action succeeds or fails, when audit history is reviewed, then actor, property, timestamp, before/after values, reason and correlation ID are available. | P70: Tampered IDs, expired sessions, approval-limit violations and cross-tenant requests are rejected; secrets and sensitive guest/payment fields are never written to logs. | Q70: Tenant/property scope; required fields; optimistic locking; timezone-safe dates; reason mandatory for overrides; currency precision; tax/rate totals; approval limit; no unbalanced or duplicate posting | R70: All revenue modules | S70: GET, POST, PUT/PATCH, DELETE /api/v1/deposit-schedule; lookup, validation and audit endpoints; idempotency for financial/booking writes; entities: folios, payments, refunds, invoices, credit_notes, cash_drawers, taxes, receivables | T70: Must Have | U70: MVP | V70: 5 | W70: S03-S04 | X70: Done | Y70: 1 | AA70: TC-058-C | AB70: Approved screen design; story reviewed with Finance Manager; dependencies, API contract, role permissions and test data identified. | AC70: Code reviewed; unit, API, UI, RBAC and integration tests pass; accessibility and responsive states verified; audit evidence captured; product owner accepts in staging. | AD70: Security/exceptions: RBAC payments.view/create/edit/cancel/approve, deny-by-default. NOTE: the payments permission rows had existed since IAM 0001 but were granted to NO role - every check denied everyone; iam 0007_payments_grants now grants them to Front Desk (view/create/edit), Reservations (view), Resort Manager, Administrator and Property IT Administrator. Waivers over Rs 5,000 need payments.approve: a request from someone without it is stored as 'requested' and the balance does NOT move until decided (verified: anita.reddy/Front Desk waived Rs 9,000 -> requested, status stayed Pending, balance unchanged Rs 13,650; admin approved -> applied; front desk got 403 on waiver-decision). Also verified: over-collection 422, double refund 422, cancelling a paid instalment 422, regenerating an existing schedule 409, optimistic-lock 409 on edit. Append-only audit for generate/create/update/cancel/collect/refund/waive/decision/reminder. GAPS STATED ON THE SCREEN: reminders are recorded, not sent (no mail/SMS transport exists), and waiver approval is decided in place because screen 042's queue still has no request-creation path.
